{
  "id": "ScoutsUpgrade",
  "Icon": "btn-unit-protoss-scout",
  "Name": "Upgrade/Name/ScoutsUpgrade",
  "class": "CUpgrade",
  "Flags": {
    "UpgradeCheat": 1
  },
  "MaxLevel": 100,
  "Alert": "UpgradeComplete",
  "ScoreCount": "MiscTechnologyCount",
  "ScoreValue": "MiscTechnologyValue",
  "WebPriority": 1,
  "LeaderAlias": "ScoutsUpgrade",
  "Race": "Prot",
  "ScoreAmount": 25,
  "EffectArray": [
    {
      "Reference": "Unit,ScoutOnboardFighter,LifeArmor",
      "Value": "0.8"
    },
    {
      "Reference": "Unit,ScoutOnboardFighter,LifeArmorLevel",
      "Value": "1"
    },
    {
      "Reference": "Unit,ScoutOnboardFighter,ShieldArmor",
      "Value": "0.6"
    },
    {
      "Reference": "Unit,ScoutOnboardFighter,ShieldArmorLevel",
      "Value": "1"
    },
    {
      "Reference": "Effect,ScoutOnboardFighterAntiMatterMissilesDisplay,Amount[0]",
      "Value": "5"
    },
    {
      "Reference": "Effect,ScoutOnboardFighterAntiMatterMissilesDamage,Amount[0]",
      "Value": "2.5"
    },
    {
      "Reference": "Weapon,ScoutOnboardFighterAntiMatterMissiles,Level[0]",
      "Value": "1"
    },
    {
      "Reference": "Weapon,Scouts,Level[0]",
      "Value": "1"
    },
    {
      "Reference": "Unit,ScoutOnboardFighter,LifeMax",
      "Value": "7"
    },
    {
      "Reference": "Unit,ScoutOnboardFighter,LifeStart",
      "Value": "7"
    },
    {
      "Reference": "Unit,ScoutOnboardFighter,ShieldsMax",
      "Value": "7"
    },
    {
      "Reference": "Unit,ScoutOnboardFighter,ShieldsStart",
      "Value": "7"
    },
    {
      "Reference": "Behavior,Escort,Modification.VitalRegenArray[Shields]",
      "Value": "0.281200"
    },
    {
      "Reference": "Unit,ScoutOnboardFighter,ReviveInfoBase[0].Resource[Minerals]",
      "Value": "1"
    },
    {
      "Reference": "Abil,CarrierUpgrade,InfoArray[Research11].Resource[Minerals]",
      "Value": "5"
    }
  ],
  "EditorCategories": "Race:Protoss,UpgradeType:Talents",
  "AffectedUnitArray": [
    "CarrierCapitalShip",
    "ScoutOnboardFighter"
  ]
}