{
  "class": "CUnit",
  "Name": {
    "frFR": "Baraquement contaminé",
    "deDE": "Verseuchtes Koloniegebäude",
    "esES": "Complejo de colonos infestado",
    "esMX": "Complejo de colonos infestados ",
    "ruRU": "Зараженный жилой модуль",
    "koKR": "감염된 거주민 수용소 ",
    "zhCN": "被感染的移民营 ",
    "zhTW": "受感染的殖民基地 ",
    "plPL": "Zainfekowana baza kolonistów",
    "itIT": "Complesso coloniale infestato",
    "ptBR": "Complexo de Colonos Infestado "
  },
  "Description": {
    "frFR": "Bâtiment civil. Génère périodiquement de l’infanterie contaminée.<br/><br/><span style=\"color: #ffff8a\">Débloque :</span><br/>- Civil contaminé",
    "deDE": "Ziviles Wohngebäude. Erzeugt regelmäßig verseuchte Infanterie.<br/><br/><span style=\"color: #ffff8a\">Ermöglicht:</span><br/>- Verseuchte Zivilisten",
    "esES": "Residencia civil. Engendra periódicamente infantería infestada.<br/><br/><span style=\"color: #ffff8a\">Permite:</span><br/>- Civiles infestados",
    "esMX": "Residencia civil. Engendra Infantería infestada periódicamente.<br/><br/><span style=\"color: #ffff8a\">Habilita:</span><br/>- Civiles infestados ",
    "ruRU": "Гражданское строение. Периодически порождает зараженных пехотинцев.<br/><br/><span style=\"color: #ffff8a\">Открывает возможности:</span><br/>– порождение зараженных мирных жителей",
    "koKR": "민간인 거주 건물입니다. 주기적으로 감염된 보병을 생성합니다.<br/><br/><span style=\"color: #ffff8a\">사용 가능:</span><br/>- 감염된 민간인 ",
    "zhCN": "民用住宅。定期孵化被感染的步兵。<br/><br/><span style=\"color: #ffff8a\">开启：</span><br/>- 被感染的平民 ",
    "zhTW": "平民住宅。每隔一段時間就會孵化受感染的平民。<br/><br/><span style=\"color: #ffff8a\">功能：</span><br/>- 孵化受感染的平民 ",
    "plPL": "Cywilna budowla mieszkalna. Co jakiś czas powija zainfekowaną piechotę.<br/><br/><span style=\"color: #ffff8a\">Udostępnia:</span><br/>– zainfekowanych cywili",
    "itIT": "Abitazione civile. Genera periodicamente fanti infestati.<br/><br/><span style=\"color: #ffff8a\">Consente:</span><br/>- Civili infestati",
    "ptBR": "Residência civil. Gera infantaria infestada periodicamente.<br/><br/><span style=\"color: #ffff8a\">Ativa:</span><br/>- Civis Infestados "
  },
  "DeathRevealFilters": "Visible;Player,Ally,Neutral,Missile,Dead,Hidden",
  "DeathRevealRadius": 3,
  "DeathRevealDuration": 4,
  "DeathRevealType": "Snapshot",
  "Race": "InfT",
  "DefaultAcquireLevel": "Offensive",
  "Response": "Acquire",
  "ResourceState": "Unknown",
  "ResourceType": "Unknown",
  "LifeStart": 1000,
  "LifeMax": 1000,
  "LifeArmorName": {
    "frFR": "Blindage bâtiment terran",
    "deDE": "Gebäudepanzerung (Terraner)",
    "esES": "Chapado de edificio terran",
    "esMX": "Coraza de edificaciones terran ",
    "ruRU": "Обшивка построек терранов",
    "koKR": "테란 건물 장갑 ",
    "zhCN": "人类建筑钢板 ",
    "zhTW": "人類建築的合金板 ",
    "plPL": "Opancerzenie budynków terran",
    "itIT": "Blindatura strutture Terran",
    "ptBR": "Revestimento de estrutura terrana "
  },
  "Mover": "Ground",
  "StationaryTurningRate": 719.4726,
  "TurningRate": 719.4726,
  "Radius": 1.6,
  "SeparationRadius": 1.6,
  "MinimapRadius": 1.6,
  "EditorCategories": "ObjectType:Structure,ObjectFamily:FactionInfested",
  "TacticalAIFilters": "-;Player,Ally,Neutral",
  "AIEvalFactor": 1,
  "Mass": 0.4,
  "FlagArray": [
    "Movable",
    "Unclickable",
    "Unhighlightable",
    "Untooltipable",
    "KillCredit",
    "ShowResources",
    "ClearRallyOnTargetLost",
    "PlayerRevivable",
    "CameraFollow",
    "PreventDefeat",
    "PenaltyRevealed",
    "UseLineOfSight",
    "TownAlert",
    "NoPortraitTalk",
    "ArmorDisabledWhileConstructing"
  ],
  "EditorFlags": [
    "BlockStructures"
  ],
  "PushPriority": 10,
  "LeaderAlias": "SICivilianStructure",
  "HotkeyAlias": "SICivilianStructure",
  "SelectAlias": "SICivilianStructure",
  "SubgroupAlias": "SICivilianStructure",
  "OccludeHeight": 0.75,
  "TacticalAI": "SICivilianStructure",
  "AIEvaluateAlias": "SICivilianStructure",
  "ReviveType": "SICivilianStructure",
  "PawnItemReduction": 1,
  "Fidget": {
    "DelayMax": 30,
    "DelayMin": 10,
    "DistanceMax": 4,
    "DistanceMin": 1,
    "TurnAngle": 90,
    "TurningRate": 90,
    "ChanceArray": {
      "Idle": 100
    }
  },
  "ReviveInfoBase": [
    {
      "Charge": {
        "Link": "SICivilianStructure/Revive",
        "Location": "Unit"
      },
      "Cooldown": {
        "Link": "SICivilianStructure/Revive",
        "Location": "Unit"
      }
    }
  ],
  "InnerRadiusSafetyMultiplier": 1,
  "ArmorType": "Unknown",
  "Facing": 315,
  "FogVisibility": "Snapshot",
  "PlaneArray": [
    "Ground"
  ],
  "Collide": [
    "Burrow",
    "Ground",
    "Structure",
    "Small"
  ],
  "Attributes": [
    "Armored",
    "Biological",
    "Mechanical",
    "Structure"
  ],
  "LifeArmor": 1,
  "LifeRegenRate": 0.2734,
  "Sight": 9,
  "CostCategory": "Economy",
  "CostResource": {
    "Minerals": 200
  },
  "RepairTime": 65,
  "AttackTargetPriority": 11,
  "AbilArray": [
    "BuildInProgress",
    "que5",
    "SIInfestedCivilianStructureResearch",
    "SIStukovPlaceHordeRally",
    "SICivilianStructureLiftOff",
    "SICivilianStructureSpawnCivilian"
  ],
  "BehaviorArray": [
    "SICivilianStructureSpawnCivilian",
    "OnCreep",
    "ZergBuildingNotOnCreep",
    "ZergBuildingDies6",
    "ChronoBoostTarget"
  ],
  "CardLayouts": {
    "Root": [
      {
        "Info": {},
        "Cost": {
          "Minerals": 0,
          "Vespene": 0,
          "Terazine": 0,
          "Custom": 0,
          "Energy": 0,
          "Life": 0,
          "Shields": 0,
          "Food": 0
        },
        "Row": 1,
        "Column": 4,
        "Type": "AbilCmd",
        "AbilCmd": "Rally,Rally1",
        "id": "Rally",
        "Icon": "btn-ability-terran-setrallypoint",
        "Name": {
          "frFR": "Définir le point de ralliement ",
          "deDE": "Sammelpunkt festlegen ",
          "esES": "Establecer punto de reunión ",
          "esMX": "Establecer punto de reunión ",
          "ruRU": "Задать точку сбора ",
          "koKR": "집결 지점 설정 ",
          "zhCN": "设定集结点 ",
          "zhTW": "設定集結點 ",
          "plPL": "Ustaw punkt zborny ",
          "itIT": "Imposta punto di raduno",
          "ptBR": "Definir ponto de concentração "
        },
        "Tooltip": {
          "frFR": "Envoie les unités construites au point désigné. Les ouvriers envoyés sur des ressources commenceront automatiquement la collecte. ",
          "deDE": "Schickt erstellte Einheiten zum festgelegten Punkt. Arbeiter, die zu Ressourcen geschickt werden, beginnen automatisch mit dem Abbau. ",
          "esES": "Envía a las unidades construidas al punto designado. Los obreros enviados a los recursos comenzarán a recolectar automáticamente. ",
          "esMX": "Envía las unidades construidas al punto designado. Los trabajadores reunidos en los recursos comenzarán automáticamente la recolección. ",
          "ruRU": "Отправляет созданные войска в указанную точку. Рабочие, отправленные на месторождение минералов или веспена, автоматически начнут добычу ресурсов.",
          "koKR": "생산된 유닛을 지정한 지점으로 보냅니다. 자원으로 보낸 일꾼은 자동으로 채취를 시작합니다. ",
          "zhCN": "将生成的单位派往指定地点。派往资源点的工作单位会自动开始采集。 ",
          "zhTW": "派遣所建造的單位前往指定的地點。被派往資源點的工作單位在抵達後將自動開始採集。 ",
          "plPL": "Wysyła nowowyszkolone jednostki we wskazane miejsce. Jednostki robotnicze wysłane do surowców automatycznie rozpoczną ich gromadzenie. ",
          "itIT": "Invia le unità prodotte verso il punto designato. I lavoratori radunati in prossimità di risorse inizieranno la raccolta automaticamente.",
          "ptBR": "Envia unidades construídas ao ponto designado. Os trabalhadores concentrados nos recursos começarão a extrair automaticamente. "
        }
      },
      {
        "Info": {
          "class": "CAbilEffectTarget",
          "Name": "Abil/Name/SIStukovPlaceHordeRally",
          "TechPlayer": "Upkeep",
          "EditorCategories": "Race:Protoss,AbilityorEffectType:Units",
          "TargetMessage": "Abil/TargetMessage/DefaultTargetMessage",
          "OrderArray": [
            {
              "DisplayType": "Confirm",
              "Color": "255,0,255,0",
              "Model": "Assets\\UI\\Cursors\\WayPointAttack_Void\\WayPointAttack_Void.m3",
              "LineTexture": "Assets\\Textures\\WayPointLine.dds"
            }
          ],
          "SharedFlags": {
            "DisableWhileDead": 1
          },
          "DataCollection": "SIStukovPlaceHordeRally",
          "RangeSlop": 1,
          "ArcSlop": 11.25,
          "AutoCastAcquireLevel": "Offensive",
          "AutoCastFilters": "Visible;Player,Ally",
          "Flags": {
            "AbortOnAllianceChange": 1,
            "CancelResetAutoCast": 1,
            "ChannelingMinimum": 1,
            "RangeUseCasterRadius": 1,
            "ReApproachable": 1,
            "RequireTargetVision": 0,
            "WaitToSpend": 0,
            "UpdateChargesOnLevelChange": 1,
            "BestUnit": 1,
            "Smart": 1,
            "Transient": 1
          },
          "Effect": [
            "SIStukovPlaceHordeRallyCP"
          ],
          "EffectRange": [
            "0,1000"
          ],
          "AINotifyEffect": "SIStukovPlaceHordeRally",
          "RefundArray": {
            "Approach": 1,
            "Prep": 1,
            "Cast": 1
          },
          "RefundFraction": {
            "Resource": {
              "Minerals": -1,
              "Vespene": -1,
              "Terrazine": -1,
              "Custom": -1
            },
            "Charge": -1,
            "Cooldown": -1
          },
          "UseMarkerArray": {
            "Approach": 1,
            "Prep": 1,
            "Cast": 1,
            "Channel": 1
          },
          "PauseableArray": {
            "Approach": 1,
            "Prep": 1,
            "Cast": 1,
            "Channel": 1,
            "Finish": 1
          },
          "PreemptableArray": {
            "Approach": 1,
            "Prep": 1,
            "Cast": 1,
            "Channel": 1,
            "Finish": 1
          },
          "ValidatedArray": {
            "Approach": 1,
            "Prep": 1,
            "Cast": 1,
            "Channel": 1
          },
          "DefaultError": "MustTargetUnit",
          "AcquirePriority": 3,
          "SetLastTarget": "Unknown",
          "VeterancyLevelMin": 0,
          "VeterancyLevelSkip": 0,
          "CmdButtonArray": {
            "Execute": {
              "Flags": {
                "ShowInGlossary": 1
              },
              "DefaultButtonFace": "SIStukovPlaceHordeRally"
            }
          },
          "FollowRange": 5,
          "Range": [
            500
          ],
          "Arc": 360,
          "id": "SIStukovPlaceHordeRally"
        },
        "Cost": {
          "Minerals": 0,
          "Vespene": 0,
          "Terazine": 0,
          "Custom": 0,
          "Energy": 0,
          "Life": 0,
          "Shields": 0,
          "Food": 0
        },
        "Row": 1,
        "Column": 4,
        "Type": "AbilCmd",
        "AbilCmd": "SIStukovPlaceHordeRally,Execute",
        "id": "SIStukovPlaceHordeRally",
        "Icon": "btn-ability-zerg-stukov-summonpsiemitter",
        "Name": {
          "frFR": "Déploiement d’un émetteur psi",
          "deDE": "Psi-Emitter aktivieren",
          "esES": "Desplegar emisor psiónico",
          "esMX": "Desplegar Emisor psiónico ",
          "ruRU": "Установить пси-излучатель",
          "koKR": "사이오닉 방출기 배치 ",
          "zhCN": "部署灵能发射器 ",
          "zhTW": "設置幽能發射器 ",
          "plPL": "Emiter Psioniczny",
          "itIT": "Colloca Emettitore psionico",
          "ptBR": "Implantar Emissor Psi "
        },
        "Tooltip": {
          "frFR": "Envoie toutes les unités d’infanterie, existantes et formées récemment, à l’emplacement indiqué.",
          "deDE": "Schickt alle bestehenden und neu erschaffenen verseuchten Infanterieeinheiten zu einem bestimmten Punkt.",
          "esES": "Envía a todas las unidades de infantería infestadas existentes y recién construidas al punto seleccionado.",
          "esMX": "Envía a todas las unidades de Infantería infestadas, las que tenías y las que acabas de construir, al punto designado. ",
          "ruRU": "Отправляет всех существующих и порожденных в будущем зараженных пехотинцев в указанную точку.",
          "koKR": "현재 및 새롭게 생성되는 모든 감염된 보병 유닛을 목표 지점으로 보냅니다. ",
          "zhCN": "将当前已有和后续新造的被感染的步兵单位派往指定地点。 ",
          "zhTW": "將目前已有或是即將孵化的受感染的步兵單位集結到指定地點。 ",
          "plPL": "Wysyła wszystkie istniejące i nowo powstające jednostki zainfekowanej piechoty do wyznaczonego punktu.",
          "itIT": "Invia tutte le unità di fanteria infestate esistenti e appena generate al punto designato.",
          "ptBR": "Envia todas as unidades de infantaria Infestadas existentes e recém-construídas no momento para o ponto designado. "
        }
      },
      {
        "Info": {
          "class": "CAbilQueue",
          "Name": "Abil/Name/que5",
          "TechPlayer": "Upkeep",
          "EditorCategories": "Race:Neutral,AbilityorEffectType:Structures",
          "TargetMessage": "Abil/TargetMessage/DefaultTargetMessage",
          "OrderArray": [
            {
              "DisplayType": "Confirm",
              "Color": "255,0,255,0",
              "Model": "Assets\\UI\\Cursors\\WayPointConfirm_Void\\WayPointConfirm_Void.m3",
              "LineTexture": "Assets\\Textures\\WayPointLine.dds"
            }
          ],
          "SharedFlags": {
            "DisableWhileDead": 1
          },
          "DataCollection": "que5",
          "QueueCount": 1,
          "Flags": {
            "BestUnit": 1,
            "NotifyAddOn": 1,
            "Passive": 1
          },
          "CmdButtonArray": {
            "CancelLast": {
              "DefaultButtonFace": "Cancel"
            },
            "CancelSlot": {
              "DefaultButtonFace": "CancelSlot"
            }
          },
          "QueueSize": 5,
          "id": "que5"
        },
        "Cost": {
          "Minerals": 0,
          "Vespene": 0,
          "Terazine": 0,
          "Custom": 0,
          "Energy": 0,
          "Life": 0,
          "Shields": 0,
          "Food": 0
        },
        "Row": 2,
        "Column": 4,
        "Type": "AbilCmd",
        "AbilCmd": "que5,CancelLast",
        "id": "Cancel",
        "Icon": "btn-command-cancel",
        "Name": {
          "enUS": "Cancel",
          "ruRU": "Отменить ",
          "frFR": "Annuler ",
          "deDE": "Abbrechen ",
          "esES": "Cancelar ",
          "esMX": "Cancelar ",
          "koKR": "취소 ",
          "zhCN": "取消 ",
          "zhTW": "取消 ",
          "plPL": "Anuluj ",
          "itIT": "Annulla",
          "ptBR": "Cancelar "
        },
        "Tooltip": {
          "frFR": "Abandonne l’ordre en cours et vous permet d’en donner un nouveau. ",
          "deDE": "Bricht den aktuellen Befehl ab und ermöglicht das Erteilen neuer Befehle. ",
          "esES": "Abandona la orden actual sin llevarla a cabo y te permite seleccionar una orden diferente. ",
          "esMX": "Cancela la orden actual sin ejecutarla y te permite seleccionar otra orden. ",
          "ruRU": "Отменить текущий приказ и отдать следующий. ",
          "koKR": "유닛에게 내린 지시를 취소하여 다른 지시를 받을 수 있게 합니다. ",
          "zhCN": "直接取消当前命令，让您可以选择其它命令。 ",
          "zhTW": "直接取消目前的指令，這樣可讓你選擇不同的指令。 ",
          "plPL": "Porzuca aktualny rozkaz bez wykonywania go i pozwala wybrać inny. ",
          "itIT": "Annulla l'ordine attuale e consente di selezionarne un altro.",
          "ptBR": "Cancela a ordem atual sem executá-la e permite selecionar outra ordem. "
        }
      },
      {
        "Info": {
          "class": "CAbilBuildable",
          "Name": "Abil/Name/BuildInProgress",
          "TechPlayer": "Upkeep",
          "EditorCategories": "Race:Neutral,AbilityorEffectType:Units",
          "TargetMessage": "Abil/TargetMessage/DefaultTargetMessage",
          "OrderArray": [
            {
              "DisplayType": "Confirm",
              "Color": "255,0,255,0",
              "Model": "Assets\\UI\\Cursors\\WayPointConfirm_Void\\WayPointConfirm_Void.m3",
              "LineTexture": "Assets\\Textures\\WayPointLine.dds"
            }
          ],
          "SharedFlags": {
            "DisableWhileDead": 1
          },
          "DataCollection": "BuildInProgress",
          "Activity": "UI/Building",
          "VitalStartFactor": {
            "Life": 0.1,
            "Shields": 0.1,
            "Energy": 1
          },
          "CmdButtonArray": {
            "Cancel": {
              "DefaultButtonFace": "Cancel"
            },
            "Halt": {
              "DefaultButtonFace": "Cancel"
            }
          },
          "id": "BuildInProgress"
        },
        "Cost": {
          "Minerals": 0,
          "Vespene": 0,
          "Terazine": 0,
          "Custom": 0,
          "Energy": 0,
          "Life": 0,
          "Shields": 0,
          "Food": 0
        },
        "Row": 2,
        "Column": 4,
        "Type": "AbilCmd",
        "AbilCmd": "BuildInProgress,Cancel",
        "id": "Cancel",
        "Icon": "btn-command-cancel",
        "Name": {
          "enUS": "Cancel",
          "ruRU": "Отменить ",
          "frFR": "Annuler ",
          "deDE": "Abbrechen ",
          "esES": "Cancelar ",
          "esMX": "Cancelar ",
          "koKR": "취소 ",
          "zhCN": "取消 ",
          "zhTW": "取消 ",
          "plPL": "Anuluj ",
          "itIT": "Annulla",
          "ptBR": "Cancelar "
        },
        "Tooltip": {
          "frFR": "Abandonne l’ordre en cours et vous permet d’en donner un nouveau. ",
          "deDE": "Bricht den aktuellen Befehl ab und ermöglicht das Erteilen neuer Befehle. ",
          "esES": "Abandona la orden actual sin llevarla a cabo y te permite seleccionar una orden diferente. ",
          "esMX": "Cancela la orden actual sin ejecutarla y te permite seleccionar otra orden. ",
          "ruRU": "Отменить текущий приказ и отдать следующий. ",
          "koKR": "유닛에게 내린 지시를 취소하여 다른 지시를 받을 수 있게 합니다. ",
          "zhCN": "直接取消当前命令，让您可以选择其它命令。 ",
          "zhTW": "直接取消目前的指令，這樣可讓你選擇不同的指令。 ",
          "plPL": "Porzuca aktualny rozkaz bez wykonywania go i pozwala wybrać inny. ",
          "itIT": "Annulla l'ordine attuale e consente di selezionarne un altro.",
          "ptBR": "Cancela a ordem atual sem executá-la e permite selecionar outra ordem. "
        }
      },
      {
        "Info": {
          "class": "CAbilEffectInstant",
          "Name": "Abil/Name/SICivilianStructureSpawnCivilian",
          "TechPlayer": "Upkeep",
          "EditorCategories": "Race:Neutral,AbilityorEffectType:Units",
          "TargetMessage": "Abil/TargetMessage/DefaultTargetMessage",
          "OrderArray": [
            {
              "DisplayType": "Confirm",
              "Color": "255,0,255,0",
              "Model": "Assets\\UI\\Cursors\\WayPointAttack_Void\\WayPointAttack_Void.m3",
              "LineTexture": "Assets\\Textures\\WayPointLine.dds"
            }
          ],
          "SharedFlags": {
            "DisableWhileDead": 1
          },
          "DataCollection": "SICivilianStructureSpawnCivilian",
          "RangeSlop": 1,
          "ArcSlop": 11.25,
          "AutoCastAcquireLevel": "Offensive",
          "AutoCastFilters": "Visible;Ally,Neutral,Enemy",
          "Flags": {
            "AbortOnAllianceChange": 1,
            "CancelResetAutoCast": 1,
            "ChannelingMinimum": 1,
            "RangeUseCasterRadius": 1,
            "ReApproachable": 1,
            "RequireTargetVision": 1,
            "WaitToSpend": 0,
            "UpdateChargesOnLevelChange": 1,
            "AutoCast": 1,
            "AutoCastOn": 1
          },
          "Effect": [
            "SICivilianStructureSpawnCivilianGlobalTimerDummyCP"
          ],
          "EffectRange": [
            "0,1000"
          ],
          "AINotifyEffect": "SICivilianStructureSpawnCivilian",
          "RefundArray": {
            "Approach": 1,
            "Prep": 1,
            "Cast": 1
          },
          "RefundFraction": {
            "Resource": {
              "Minerals": -1,
              "Vespene": -1,
              "Terrazine": -1,
              "Custom": -1
            },
            "Charge": -1,
            "Cooldown": -1
          },
          "UseMarkerArray": {
            "Approach": 1,
            "Prep": 1,
            "Cast": 1,
            "Channel": 1
          },
          "PauseableArray": {
            "Approach": 1,
            "Prep": 1,
            "Cast": 1,
            "Channel": 1,
            "Finish": 1
          },
          "PreemptableArray": {
            "Approach": 1,
            "Prep": 1,
            "Cast": 1,
            "Channel": 1,
            "Finish": 1
          },
          "ValidatedArray": {
            "Approach": 1,
            "Prep": 1,
            "Cast": 1,
            "Channel": 1
          },
          "DefaultError": "MustTargetUnit",
          "AcquirePriority": 3,
          "SetLastTarget": "Unknown",
          "VeterancyLevelMin": 0,
          "VeterancyLevelSkip": 0,
          "CmdButtonArray": {
            "Execute": {
              "Flags": {
                "ShowInGlossary": 1
              },
              "DefaultButtonFace": "SIInfestedCivilian",
              "Requirements": "IsSICivilianStructureRooted"
            }
          },
          "Cost": [
            {
              "Cooldown": {
                "Location": "Unit",
                "TimeStart": 60,
                "TimeUse": 60
              }
            }
          ],
          "id": "SICivilianStructureSpawnCivilian"
        },
        "Cost": {
          "Minerals": 0,
          "Vespene": 0,
          "Terazine": 0,
          "Custom": 0,
          "Energy": 0,
          "Life": 0,
          "Shields": 0,
          "Food": 0
        },
        "Row": 2,
        "Column": 0,
        "Type": "AbilCmd",
        "AbilCmd": "SICivilianStructureSpawnCivilian,Execute",
        "id": "SIInfestedCivilian",
        "Icon": "btn-unit-zerg-infestedcolonist",
        "Name": {
          "frFR": "Générer un civil contaminé",
          "deDE": "Verseuchten Zivilisten erschaffen",
          "esES": "Engendrar civil infestado",
          "esMX": "Engendrar Civil infestado ",
          "ruRU": "Породить зараженного мирного жителя",
          "koKR": "감염된 민간인 생성 ",
          "zhCN": "孵化被感染的平民 ",
          "zhTW": "孵化受感染的平民 ",
          "plPL": "Powij zainfekowanego cywila",
          "itIT": "Genera Civile infestato",
          "ptBR": "Gerar Civil Infestado "
        },
        "Tooltip": {
          "frFR": "Infanterie contaminée polyvalente. Dure <b>90</b> secondes.<br/><br/><span style=\"color: ##ffff8a\">Peut attaquer les unités terrestres.</span>",
          "deDE": "Verseuchte Allzweck-Infanterie. Bleibt <b>90</b> Sek. lang bestehen.<br/><br/><span style=\"color: ##ffff8a\">Kann Bodeneinheiten angreifen.</span>",
          "esES": "Infantería de cometido general infestada. Tiene una duración de <b>90</b> segundos.<br/><br/><span style=\"color: ##ffff8a\">Puede atacar a unidades terrestres.</span>",
          "esMX": "Infantería infestada de uso general. Dura <b>90</b> segundos.<br/><br/><span style=\"color: ##ffff8a\">Ataca a unidades terrestres.</span> ",
          "ruRU": "Зараженная пехота общего назначения. Продолжительность жизни – <b>90</b> сек.<br/><br/><span style=\"color: ##ffff8a\">Атакует только наземные цели.</span>",
          "koKR": "감염된 다목적 보병입니다. <b>90</b>초 동안 전장에 머뭅니다.<br/><br/><span style=\"color: ##ffff8a\">지상 유닛 공격 가능</span> ",
          "zhCN": "通用型被感染的步兵，持续存在<b>90</b>秒。<br/><br/><span style=\"color: ##ffff8a\">可以对地。</span> ",
          "zhTW": "泛用型受感染的步兵。可存活<b>90</b>秒。<br/><br/><span style=\"color: ##ffff8a\">可攻擊地面單位。</span> ",
          "plPL": "Zainfekowana piechota wielozadaniowa. Żyje <b>90</b> sek.<br/><br/><span style=\"color: ##ffff8a\">Może atakować jednostki naziemne.</span>",
          "itIT": "Fante generico infestato. Dura <b>90</b> secondi.<br/><br/><span style=\"color: ##ffff8a\">Può attaccare unità terrestri.</span>",
          "ptBR": "Infantaria infestada de uso geral. Tem uma duração de <b>90</b> segundos.<br/><br/><span style=\"color: ##ffff8a\">Ataca unidades terrestres.</span> "
        }
      },
      {
        "Upgrade": "SIBarracksTrainInfestedCivilianLevel2",
        "Info": {
          "Button": {
            "Flags": {
              "AllowMinimap": 0
            },
            "DefaultButtonFace": "ResearchSIBarracksTrainInfestedCivilianLevel2",
            "Requirements": "LearnSIBarracksTrainInfestedCivilianLevel2"
          },
          "Resource": {
            "Minerals": 200
          },
          "Time": 120,
          "Upgrade": "SIBarracksTrainInfestedCivilianLevel2"
        },
        "Time": 120,
        "Cost": {
          "Minerals": 200,
          "Vespene": 0,
          "Terazine": 0,
          "Custom": 0,
          "Energy": 0,
          "Life": 0,
          "Shields": 0,
          "Food": 0
        },
        "Row": 0,
        "Column": 0,
        "Type": "AbilCmd",
        "AbilCmd": "SIInfestedCivilianStructureResearch,Research1",
        "id": "ResearchSIBarracksTrainInfestedCivilianLevel2",
        "Icon": "btn-ability-stukov-infestedcivilianstructurelv1",
        "Name": {
          "frFR": "Évolution Contamination - Niv. 1",
          "deDE": "Verseuchung der Stufe 1 entwickeln",
          "esES": "Evolucionar nivel de infestación 1",
          "esMX": "Evolucionar Infestación nivel 1 ",
          "ruRU": "Развить заражение 1-го уровня",
          "koKR": "감염 진화 1단계 ",
          "zhCN": "进化1级感染 ",
          "zhTW": "進化感染等級1 ",
          "plPL": "Wyewoluuj infekcję poziomu 1",
          "itIT": "Evolvi Infestazione livello 1",
          "ptBR": "Evoluir Infestação Nível 1 "
        },
        "Tooltip": {
          "frFR": "Augmente de 500 les points de vie du <span style=\"color: #ffff8a\">baraquement contaminé</span> qui génère 8 <span style=\"color: #ffff8a\">civils contaminés</span> supplémentaires à la fois, pour un total de 16.",
          "deDE": "<span style=\"color: #ffff8a\">Verseuchte Koloniegebäude</span> erhalten zusätzlich +500 Trefferpunkte und erschaffen 8 weitere <span style=\"color: #ffff8a\">verseuchte Zivilisten</span> gleichzeitig, insgesamt 16.",
          "esES": "El <span style=\"color: #ffff8a\">complejo de colonos infestado</span> obtiene 500 de vida y engendra 8 <span style=\"color: #ffff8a\">civiles infestados</span> adicionales cada vez, hasta un total de 16.",
          "esMX": "El <span style=\"color: #ffff8a\">Complejo de colonos infestados</span> obtiene 500 de vida y engendra 8 <span style=\"color: #ffff8a\">Civiles infestados</span> más a la vez para alcanzar un total de 16. ",
          "ruRU": "Увеличивает запас прочности <span style=\"color: #ffff8a\">зараженного жилого модуля</span> на 500 ед., и позволяет ему каждый раз дополнительно порождать 8 <span style=\"color: #ffff8a\">зараженных мирных жителей</span> (всего 16).",
          "koKR": "<span style=\"color: #ffff8a\">감염된 거주민 수용소</span>의 체력이 500만큼 증가하고 추가로 한 번에 8기, 총 16기의 <span style=\"color: #ffff8a\">감염된 민간인</span>을 생성합니다. ",
          "zhCN": "<span style=\"color: #ffff8a\">被感染的移民营</span>获得500点生命值，并且同一时间可以孵化额外8名<span style=\"color: #ffff8a\">被感染的平民</span>，总共16名。 ",
          "zhTW": "<span style=\"color: #ffff8a\">受感染的殖民基地</span>生命值提高500點，一次可額外孵化8個<span style=\"color: #ffff8a\">受感染的平民</span>，共孵化16個。 ",
          "plPL": "<span style=\"color: #ffff8a\">Zainfekowana baza kolonistów</span> otrzymuje +500 pkt. życia i powija dodatkowych 8 <span style=\"color: #ffff8a\">zainfekowanych cywili</span> (łącznie 16).",
          "itIT": "Aumenta di 500 la vita del <span style=\"color: #ffff8a\">Complesso coloniale infestato</span> e genera 8 <span style=\"color: #ffff8a\">Civili infestati</span> aggiuntivi alla volta, per un totale di 16.",
          "ptBR": "O <span style=\"color: #ffff8a\">Complexo de Colonos Infestado</span> ganha 500 pontos de vida e gera 8 <span style=\"color: #ffff8a\">Civis Infestados</span> adicionais por vez, em um total de 16. "
        }
      },
      {
        "Upgrade": "SIBarracksTrainInfestedCivilianLevel3",
        "Info": {
          "Button": {
            "Flags": {
              "AllowMinimap": 0
            },
            "DefaultButtonFace": "ResearchSIBarracksTrainInfestedCivilianLevel3",
            "Requirements": "LearnSIBarracksTrainInfestedCivilianLevel3"
          },
          "Resource": {
            "Minerals": 300,
            "Vespene": 100
          },
          "Time": 120,
          "Upgrade": "SIBarracksTrainInfestedCivilianLevel3"
        },
        "Time": 120,
        "Cost": {
          "Minerals": 300,
          "Vespene": 100,
          "Terazine": 0,
          "Custom": 0,
          "Energy": 0,
          "Life": 0,
          "Shields": 0,
          "Food": 0
        },
        "Row": 0,
        "Column": 0,
        "Type": "AbilCmd",
        "AbilCmd": "SIInfestedCivilianStructureResearch,Research2",
        "id": "ResearchSIBarracksTrainInfestedCivilianLevel3",
        "Icon": "btn-ability-stukov-infestedcivilianstructurelv2",
        "Name": {
          "frFR": "Évolution Contamination - Niv. 2",
          "deDE": "Verseuchung der Stufe 2 entwickeln",
          "esES": "Evolucionar nivel de infestación 2",
          "esMX": "Evolucionar Infestación nivel 2 ",
          "ruRU": "Развить заражение 2-го уровня",
          "koKR": "감염 진화 2단계 ",
          "zhCN": "进化2级感染 ",
          "zhTW": "進化感染等級2 ",
          "plPL": "Wyewoluuj infekcję poziomu 2",
          "itIT": "Evolvi Infestazione livello 2",
          "ptBR": "Evoluir Infestação Nível 2 "
        },
        "Tooltip": {
          "frFR": "Augmente de 500 les points de vie du <span style=\"color: #ffff8a\">baraquement contaminé</span> qui génère 16 <span style=\"color: #ffff8a\">civils contaminés</span> supplémentaires à la fois, pour un total de 32.",
          "deDE": "<span style=\"color: #ffff8a\">Verseuchte Koloniegebäude</span> erhalten zusätzlich +500 Trefferpunkte und erschaffen 16 weitere <span style=\"color: #ffff8a\">verseuchte Zivilisten</span> gleichzeitig, insgesamt 32.",
          "esES": "El <span style=\"color: #ffff8a\">complejo de colonos infestado</span> obtiene 500 de vida y engendra 16 <span style=\"color: #ffff8a\">civiles infestados</span> adicionales cada vez, hasta un total de 32.",
          "esMX": "El <span style=\"color: #ffff8a\">Complejo de colonos infestados</span> obtiene 500 de vida y engendra 16 <span style=\"color: #ffff8a\">Civiles infestados</span> más de una vez para alcanzar un total de 32. ",
          "ruRU": "Увеличивает запас прочности <span style=\"color: #ffff8a\">зараженного жилого модуля</span> на 500 ед., и позволяет ему каждый раз дополнительно порождать 16 <span style=\"color: #ffff8a\">зараженных мирных жителей</span> (всего 32).",
          "koKR": "<span style=\"color: #ffff8a\">감염된 거주민 수용소</span>의 체력이 500만큼 증가하고 추가로 한 번에 16기, 총 32기의 <span style=\"color: #ffff8a\">감염된 민간인</span>을 생성합니다. ",
          "zhCN": "<span style=\"color: #ffff8a\">被感染的移民营</span>额外获得500点生命值，并且同一时间可以孵化额外16名<span style=\"color: #ffff8a\">被感染的平民</span>，总共32名。 ",
          "zhTW": "<span style=\"color: #ffff8a\">受感染的殖民基地</span>生命值再提高500點，一次可額外孵化16個<span style=\"color: #ffff8a\">受感染的平民</span>，共孵化32個。 ",
          "plPL": "<span style=\"color: #ffff8a\">Zainfekowana baza kolonistów</span> otrzymuje +500 pkt. życia i powija dodatkowych 16 <span style=\"color: #ffff8a\">zainfekowanych cywili</span> (łącznie 32).",
          "itIT": "Aumenta ulteriormente di 500 la vita del <span style=\"color: #ffff8a\">Complesso coloniale infestato</span> e genera 16 <span style=\"color: #ffff8a\">Civili infestati</span> aggiuntivi alla volta, per un totale di 32.",
          "ptBR": "O <span style=\"color: #ffff8a\">Complexo de Colonos Infestado</span> ganha 500 pontos de vida adicionais e gera 16 <span style=\"color: #ffff8a\">Civis Infestados</span> adicionais por vez, em um total de 32. "
        }
      },
      {
        "Upgrade": "SIBarracksTrainInfestedCivilianLevel4",
        "Info": {
          "Button": {
            "Flags": {
              "AllowMinimap": 0
            },
            "DefaultButtonFace": "ResearchSIBarracksTrainInfestedCivilianLevel4",
            "State": "Restricted",
            "Requirements": "LearnSIBarracksTrainInfestedCivilianLevel4"
          },
          "Resource": {
            "Minerals": 400,
            "Vespene": 200
          },
          "Time": 120,
          "Upgrade": "SIBarracksTrainInfestedCivilianLevel4"
        },
        "Time": 120,
        "Cost": {
          "Minerals": 400,
          "Vespene": 200,
          "Terazine": 0,
          "Custom": 0,
          "Energy": 0,
          "Life": 0,
          "Shields": 0,
          "Food": 0
        },
        "Row": 0,
        "Column": 0,
        "Type": "AbilCmd",
        "AbilCmd": "SIInfestedCivilianStructureResearch,Research3",
        "id": "ResearchSIBarracksTrainInfestedCivilianLevel4",
        "Icon": "btn-ability-stukov-infestedcivilianstructure_lv3",
        "Name": {
          "frFR": "Évolution Contamination - Niv. 3",
          "deDE": "Verseuchung der Stufe 3 entwickeln",
          "esES": "Evolucionar nivel de infestación 3",
          "esMX": "Evolucionar Infestación nivel 3 ",
          "ruRU": "Развить заражение 3-го уровня",
          "koKR": "감염 진화 3단계 ",
          "zhCN": "进化3级感染 ",
          "zhTW": "進化感染等級3 ",
          "plPL": "Wyewoluuj infekcję poziomu 3",
          "itIT": "Evolvi Infestazione livello 3",
          "ptBR": "Evoluir Infestação Nível 3 "
        },
        "Tooltip": {
          "frFR": "Augmente de 500 les points de vie du <span style=\"color: #ffff8a\">baraquement contaminé</span> qui génère 32 <span style=\"color: #ffff8a\">civils contaminés</span> supplémentaires à la fois, pour un total de 64.",
          "deDE": "<span style=\"color: #ffff8a\">Verseuchte Koloniegebäude</span> erhalten zusätzlich +500 Trefferpunkte und erschaffen 32 weitere <span style=\"color: #ffff8a\">verseuchte Zivilisten</span> gleichzeitig, insgesamt 64.",
          "esES": "El <span style=\"color: #ffff8a\">complejo de colonos infestado</span> obtiene 500 de vida y engendra 32 <span style=\"color: #ffff8a\">civiles infestados</span> adicionales cada vez, hasta un total de 64.",
          "esMX": "El <span style=\"color: #ffff8a\">Complejo de colonos infestados</span> obtiene 500 de vida y engendra 32 <span style=\"color: #ffff8a\">Civiles infestados</span> más de una vez para alcanzar un total de 64. ",
          "ruRU": "Увеличивает запас прочности <span style=\"color: #ffff8a\">зараженного жилого модуля</span> на 500 ед., и позволяет ему каждый раз дополнительно порождать 32 <span style=\"color: #ffff8a\">зараженных мирных жителя</span> (всего 64).",
          "koKR": "<span style=\"color: #ffff8a\">감염된 거주민 수용소</span>의 체력이 500만큼 증가하고 추가로 한 번에 32기, 총 64기의 <span style=\"color: #ffff8a\">감염된 민간인</span>을 생성합니다. ",
          "zhCN": "<span style=\"color: #ffff8a\">被感染的移民营</span>额外获得500点生命值，并且同一时间可以孵化额外32名<span style=\"color: #ffff8a\">被感染的平民</span>，总共64名。 ",
          "zhTW": "<span style=\"color: #ffff8a\">受感染的殖民基地</span>生命值再提高500點，一次可額外孵化32個<span style=\"color: #ffff8a\">受感染的平民</span>，共孵化64個。 ",
          "plPL": "<span style=\"color: #ffff8a\">Zainfekowana baza kolonistów</span> otrzymuje +500 pkt. życia i powija dodatkowych 32 <span style=\"color: #ffff8a\">zainfekowanych cywili</span> (łącznie 64).",
          "itIT": "Aumenta ulteriormente di 500 la vita del <span style=\"color: #ffff8a\">Complesso coloniale infestato</span> e genera 32 <span style=\"color: #ffff8a\">Civili infestati</span> aggiuntivi alla volta, per un totale di 64.",
          "ptBR": "O <span style=\"color: #ffff8a\">Complexo de Colonos Infestado</span> ganha 500 pontos de vida adicionais e gera 32 <span style=\"color: #ffff8a\">Civis Infestados</span> adicionais por vez, em um total de 64. "
        }
      },
      {
        "Cost": {
          "Minerals": 0,
          "Vespene": 0,
          "Terazine": 0,
          "Custom": 0,
          "Energy": 0,
          "Life": 0,
          "Shields": 0,
          "Food": 0
        },
        "Row": 0,
        "Column": 0,
        "Type": "Passive",
        "id": "EvolveInfestationLevel3Locked",
        "Icon": "sc2_ui_ingame_storymode_panel_faction_lock",
        "Name": {
          "frFR": "Évolution Contamination - Niv. 3",
          "deDE": "Verseuchung der Stufe 3 entwickeln",
          "esES": "Evolucionar nivel de infestación 3",
          "esMX": "Evolucionar Infestación nivel 3 ",
          "ruRU": "Развить заражение 3-го уровня",
          "koKR": "감염 진화 3단계 ",
          "zhCN": "进化3级感染 ",
          "zhTW": "進化感染等級3 ",
          "plPL": "Wyewoluuj infekcję poziomu 3",
          "itIT": "Evolvi Infestazione livello 3",
          "ptBR": "Evoluir Infestação Nível 3 "
        },
        "Tooltip": {
          "frFR": "Cette amélioration est débloquée au niveau de commandant 3.",
          "deDE": "Dieses Upgrade wird erst ab Kommandantenstufe 3 freigeschaltet.",
          "esES": "Esta mejora se desbloquea al alcanzar el nivel 3 de comandante.",
          "esMX": "Esta mejora se desbloquea en el nivel de Comandante 3. ",
          "ruRU": "Откройте доступ, достигнув 3-го уровня командира.",
          "koKR": "이 업그레이드는 사령관이 3 레벨이 되면 사용할 수 있습니다. ",
          "zhCN": "该科技将在指挥官等级3时解锁。 ",
          "zhTW": "指揮官達到等級3可解鎖此項升級。 ",
          "plPL": "Ulepszenie zostanie odblokowane na 3 poziomie dowódcy.",
          "itIT": "Questo potenziamento è sbloccato al livello comandante 3.",
          "ptBR": "Este aprimoramento se desbloqueará no Nível de Comandante 3. "
        }
      },
      {
        "Info": {
          "SectionArray": {
            "Actor": {
              "DurationArray": {
                "Duration": 1.5
              }
            },
            "Mover": {
              "DurationArray": {
                "Duration": 1.6333
              }
            },
            "Stats": {
              "DurationArray": {
                "Delay": 2
              }
            }
          },
          "Unit": "SICivilianStructureFlying"
        },
        "Unit": "SICivilianStructureFlying",
        "Cost": {
          "Minerals": 200,
          "Vespene": 0,
          "Terazine": 0,
          "Custom": 0,
          "Energy": 0,
          "Life": 0,
          "Shields": 0,
          "Food": 0
        },
        "Row": 2,
        "Column": 3,
        "Type": "AbilCmd",
        "AbilCmd": "SICivilianStructureLiftOff,Execute",
        "id": "SIUproot",
        "Icon": "btn-ability-zerg-uproot-color",
        "Name": {
          "frFR": "Déraciner",
          "deDE": "Entwurzeln",
          "esES": "Desarraigar",
          "esMX": "Desarraigar ",
          "ruRU": "Выкопаться",
          "koKR": "뿌리 들기 ",
          "zhCN": "站起 ",
          "zhTW": "拔根 ",
          "plPL": "Wykorzeń",
          "itIT": "Sradica",
          "ptBR": "Desenraizar "
        },
        "Tooltip": {
          "frFR": "Déracine le bâtiment, lui permettant de se déplacer librement. Il sera impossible de produire des unités, rechercher des améliorations ou utiliser des capacités spéciales avant l’enracinement.",
          "deDE": "Entwurzelt das Gebäude, sodass es sich frei bewegen kann. Es können keine Einheiten erschaffen, Upgrades erforscht oder Fähigkeiten eingesetzt werden, bis das Gebäude wieder verwurzelt ist.",
          "esES": "Desarraiga la estructura, lo que le permite moverse con libertad. No puede producir unidades, investigar mejoras ni usar habilidades hasta que se arraigue.",
          "esMX": "Desarraiga la estructura y le permite moverse con libertad. Hasta que se arraigue otra vez, no podrá producir unidades, investigar mejoras ni usar habilidades. ",
          "ruRU": "Выкопать строение, дав ему возможность свободно передвигаться. Строение не сможет производить войска, проводить исследования, а также использовать специальные возможности, пока не окопается.",
          "koKR": "구조물의 뿌리를 들어 자유롭게 이동할 수 있게 만듭니다. 다시 뿌리를 박을 때까지 유닛 생산, 업그레이드 연구, 능력 사용이 불가능합니다. ",
          "zhCN": "使建筑站起，允许其可以自由移动。在扎根之前无法生产单位、研究升级、或者使用技能。 ",
          "zhTW": "命令建築拔根，使它能自由移動。直到再度扎根前，無法生產單位、研發升級或使用技能。 ",
          "plPL": "Wykorzenia budowlę i pozwala jej się swobodnie przemieszczać. Nie pozwala produkować jednostek, opracowywać ulepszeń ani korzystać ze zdolności, dopóki budowla nie zostanie znowu zakorzeniona.",
          "itIT": "Sradica la struttura, consentendole di spostarsi liberamente. Finché non si radica, non è in grado di produrre unità, ricercare potenziamenti o usare abilità.",
          "ptBR": "Desenraiza a estrutura, permitindo que se mova livremente. Ela não pode produzir unidades, pesquisar aprimoramentos ou usar habilidades até ser enraizada. "
        }
      },
      {
        "Upgrade": "StukovInfestedInfestedCivilianLeapAttack",
        "Info": {
          "Button": {
            "Flags": {
              "AllowMinimap": 0
            },
            "DefaultButtonFace": "EvolveStukovInfestedInfestedCivilianLeap",
            "Requirements": "LearnStukovInfestedInfestedCivilianLeapAttack"
          },
          "Resource": {
            "Minerals": 100,
            "Vespene": 100
          },
          "Time": 60,
          "Upgrade": "StukovInfestedInfestedCivilianLeapAttack"
        },
        "Time": 60,
        "Cost": {
          "Minerals": 100,
          "Vespene": 100,
          "Terazine": 0,
          "Custom": 0,
          "Energy": 0,
          "Life": 0,
          "Shields": 0,
          "Food": 0
        },
        "Row": 1,
        "Column": 0,
        "Type": "AbilCmd",
        "AbilCmd": "SIInfestedCivilianStructureResearch,Research11",
        "id": "EvolveStukovInfestedInfestedCivilianLeap",
        "Icon": "btn-upgrade-zerg-stukov-infestedciviliansleap",
        "Name": {
          "frFR": "Rechercher Métabolisme anaérobie",
          "deDE": "Erhöhte Sprungkraft erforschen",
          "esES": "Investigar mejora anaeróbica",
          "esMX": "Investigar Mejora anaeróbica ",
          "ruRU": "Разработать анаэробное усиление",
          "koKR": "혐기성 도약 연구 ",
          "zhCN": "研究厌氧强化 ",
          "zhTW": "研發瞬間體能強化 ",
          "plPL": "Opracuj wzmocnienie anaerobowe",
          "itIT": "Ricerca Incremento anaerobico",
          "ptBR": "Pesquisar Aprimoramento Anaeróbico "
        },
        "Tooltip": {
          "frFR": "Permet aux <span style=\"color: #ffff8a\">civils contaminés</span> de bondir rapidement en direction des unités terrestres ennemies proches.",
          "deDE": "Ermöglicht es <span style=\"color: #ffff8a\">verseuchten Zivilisten</span>, schnell zu einer feindlichen Bodeneinheit in der Nähe zu springen.",
          "esES": "Permite a los <span style=\"color: #ffff8a\">civiles infestados</span> saltar rápidamente hacia unidades terrestres enemigas cercanas.",
          "esMX": "Permite que los <span style=\"color: #ffff8a\">Civiles infestados</span> salten rápidamente hacia las unidades terrestres enemigas cercanas. ",
          "ruRU": "Позволяет <span style=\"color: #ffff8a\">зараженным мирным жителям</span> быстро прыгать к находящимся поблизости наземным боевым единицам противника.",
          "koKR": "<span style=\"color: #ffff8a\">감염된 민간인</span>이 주위의 적 지상 유닛에게 빠르게 도약할 수 있게 합니다. ",
          "zhCN": "允许<span style=\"color: #ffff8a\">被感染的平民</span>快速扑向附近的敌方地面单位。 ",
          "zhTW": "讓<span style=\"color: #ffff8a\">受感染的平民</span>可快速躍向附近的敵方地面單位。 ",
          "plPL": "Pozwala <span style=\"color: #ffff8a\">zainfekowanym cywilom</span> szybko doskakiwać do pobliskich jednostek naziemnych wroga.",
          "itIT": "Consente ai <span style=\"color: #ffff8a\">Civili infestati</span> di saltare rapidamente verso le unità terrestri nemiche.",
          "ptBR": "Permite que <span style=\"color: #ffff8a\">Civis Infestados</span> saltem rapidamente na direção de unidades terrestres inimigas próximas. "
        }
      },
      {
        "Upgrade": "StukovInfestedCivilianSpawnBroodlingOnDeath",
        "Info": {
          "Button": {
            "Flags": {
              "AllowMinimap": 0
            },
            "DefaultButtonFace": "EvolveStukovInfestedCivilianSpawnBroodlingsOnDeath",
            "Requirements": "LearnStukovInfestedCivilianSpawnBroodlingOnDeath"
          },
          "Resource": {
            "Minerals": 150,
            "Vespene": 150
          },
          "Time": 90,
          "Upgrade": "StukovInfestedCivilianSpawnBroodlingOnDeath"
        },
        "Time": 90,
        "Cost": {
          "Minerals": 150,
          "Vespene": 150,
          "Terazine": 0,
          "Custom": 0,
          "Energy": 0,
          "Life": 0,
          "Shields": 0,
          "Food": 0
        },
        "Row": 1,
        "Column": 1,
        "Type": "AbilCmd",
        "AbilCmd": "SIInfestedCivilianStructureResearch,Research10",
        "id": "EvolveStukovInfestedCivilianSpawnBroodlingsOnDeath",
        "Icon": "btn-upgrade-zerg-stukov-infestedspawnbroodling",
        "Name": {
          "frFR": "Évolution Incubation de vermine",
          "deDE": "Parasitenbefall entwickeln",
          "esES": "Evolucionar gestación de crías",
          "esMX": "Evolucionar Gestación de Ácaros ",
          "ruRU": "Развить созревание симбионта",
          "koKR": "공생충 잉태 진화 ",
          "zhCN": "进化巢虫育生 ",
          "zhTW": "進化寄生蟲宿主 ",
          "plPL": "Wyewoluuj rozwój pomiotów",
          "itIT": "Evolvi Gestazione Progenidi",
          "ptBR": "Evoluir Gestação de Parasitoides "
        },
        "Tooltip": {
          "frFR": "Les <span style=\"color: #ffff8a\">civils contaminés</span> génèrent une vermine quand ils meurent.",
          "deDE": "Aus <span style=\"color: #ffff8a\">verseuchten Zivilisten</span> schlüpft nach ihrem Tod ein Brütling.",
          "esES": "Los <span style=\"color: #ffff8a\">civiles infestados</span> engendran una cría al morir.",
          "esMX": "Los <span style=\"color: #ffff8a\">Civiles infestados</span> engendran un Ácaro cuando mueren. ",
          "ruRU": "<span style=\"color: #ffff8a\">Зараженные мирные жители</span> порождают симбионтов в момент гибели.",
          "koKR": "<span style=\"color: #ffff8a\">감염된 민간인</span>이 죽으면 공생충 한 마리를 생성합니다. ",
          "zhCN": "<span style=\"color: #ffff8a\">被感染的平民</span>死后会孵化一只巢虫。 ",
          "zhTW": "<span style=\"color: #ffff8a\">受感染的平民</span>死亡時會孵化寄生蟲。 ",
          "plPL": "<span style=\"color: #ffff8a\">Zainfekowani cywile</span> powijają w chwili śmierci pomioty.",
          "itIT": "I <span style=\"color: #ffff8a\">Civili infestati</span> generano un Progenide alla morte.",
          "ptBR": "<span style=\"color: #ffff8a\">Civis Infestados</span> geram um Parasitoide ao morrer. "
        }
      },
      {
        "Cost": {
          "Minerals": 0,
          "Vespene": 0,
          "Terazine": 0,
          "Custom": 0,
          "Energy": 0,
          "Life": 0,
          "Shields": 0,
          "Food": 0
        },
        "Row": 1,
        "Column": 1,
        "Type": "Passive",
        "id": "EvolveBroodlingGestationLocked",
        "Icon": "sc2_ui_ingame_storymode_panel_faction_lock",
        "Name": {
          "frFR": "Évolution Incubation de vermine",
          "deDE": "Parasitenbefall entwickeln",
          "esES": "Evolucionar gestación de crías",
          "esMX": "Evolucionar Gestación de Ácaros ",
          "ruRU": "Развить созревание симбионта",
          "koKR": "공생충 잉태 진화 ",
          "zhCN": "进化巢虫育生 ",
          "zhTW": "進化寄生蟲宿主 ",
          "plPL": "Wyewoluuj rozwój pomiotów",
          "itIT": "Evolvi Gestazione Progenidi",
          "ptBR": "Evoluir Gestação de Parasitoides "
        },
        "Tooltip": {
          "frFR": "Cette amélioration est débloquée au niveau de commandant 7.",
          "deDE": "Dieses Upgrade wird erst ab Kommandantenstufe 7 freigeschaltet.",
          "esES": "Esta mejora se desbloquea al alcanzar el nivel 7 de comandante.",
          "esMX": "Esta mejora se desbloquea en el nivel de Comandante 7. ",
          "ruRU": "Откройте доступ, достигнув 7-го уровня командира.",
          "koKR": "이 업그레이드는 사령관이 7 레벨이 되면 사용할 수 있습니다. ",
          "zhCN": "该科技将在指挥官等级7时解锁。 ",
          "zhTW": "指揮官達到等級7可解鎖此項升級。 ",
          "plPL": "Ulepszenie zostanie odblokowane na 7 poziomie dowódcy.",
          "itIT": "Questo potenziamento è sbloccato al livello comandante 7.",
          "ptBR": "Este aprimoramento se desbloqueará no Nível de Comandante 7. "
        }
      },
      {
        "Cost": {
          "Minerals": 0,
          "Vespene": 0,
          "Terazine": 0,
          "Custom": 0,
          "Energy": 0,
          "Life": 0,
          "Shields": 0,
          "Food": 0
        },
        "Row": 1,
        "Column": 2,
        "Type": "Passive",
        "id": "MasteryStukovUnitRegenSpeedAppend",
        "Icon": "btn-upgrade-zerg-stukov-regenrate",
        "Name": {
          "frFR": "Cicatrisation des tissus",
          "deDE": "Rekonstruktives Gewebe",
          "esES": "Tejido reconstructivo",
          "esMX": "Tejido reconstructivo ",
          "ruRU": "Восстановительная ткань",
          "koKR": "조직 복원 ",
          "zhCN": "肌理重构 ",
          "zhTW": "組織重建 ",
          "plPL": "Regeneracyjne tkanki",
          "itIT": "Tessuto autoricostituente",
          "ptBR": "Tecido Reconstrutivo "
        },
        "Tooltip": {
          "frFR": "<span style=\"color: #FFFF8A\">Maîtrise :</span> les unités générées par ce bâtiment récupèrent <span style=\"color: #FFFF8A\"><b>0.0</b></span> points de vie par seconde.",
          "deDE": "<span style=\"color: #FFFF8A\">Meisterung:</span> Von diesem Gebäude erschaffene Einheiten regenerieren <span style=\"color: #FFFF8A\"><b>0.0</b></span> Trefferpunkte pro Sekunde.",
          "esES": "<span style=\"color: #FFFF8A\">Maestría:</span> Las unidades engendradas en esta estructura regeneran <span style=\"color: #FFFF8A\"><b>0.0</b></span> de vida por segundo.",
          "esMX": "<span style=\"color: #FFFF8A\">Maestría:</span> Las unidades engendradas desde esta estructura regeneran <span style=\"color: #FFFF8A\"><b>0.0</b></span> de vida por segundo. ",
          "ruRU": "<span style=\"color: #FFFF8A\">Умение:</span> боевые единицы, порождаемые в этом строении, восстанавливают <span style=\"color: #FFFF8A\"><b>0.0</b></span> ед. здоровья или прочности в секунду.",
          "koKR": "<span style=\"color: #FFFF8A\">마스터:</span> 이 구조물에서 생성한 유닛이 초당 <span style=\"color: #FFFF8A\"><b>0.0</b></span>의 체력을 회복합니다. ",
          "zhCN": "<span style=\"color: #FFFF8A\">精通：</span>从这座建筑孵化的单位每秒恢复<span style=\"color: #FFFF8A\"><b>0.0</b></span>点生命值。  ",
          "zhTW": "<span style=\"color: #FFFF8A\">大師：</span>此建築生產的單位每秒恢復<span style=\"color: #FFFF8A\"><b>0.0</b></span>點生命值。",
          "plPL": "<span style=\"color: #FFFF8A\">Poziom mistrzowski:</span> Jednostki powijane w tej budowli odzyskują <span style=\"color: #FFFF8A\"><b>0.0</b></span> pkt. życia na sekundę.",
          "itIT": "<span style=\"color: #FFFF8A\">Maestria:</span> Le unità di questa struttura rigenerano <span style=\"color: #FFFF8A\"><b>0.0</b></span> punti vita al secondo.",
          "ptBR": "<span style=\"color: #FFFF8A\">Maestria:</span> Unidades implantadas por esta estrutura regeneram <span style=\"color: #FFFF8A\"><b>0.0</b></span> de vida por segundo. "
        }
      },
      {
        "Cost": {
          "Minerals": 0,
          "Vespene": 0,
          "Terazine": 0,
          "Custom": 0,
          "Energy": 0,
          "Life": 0,
          "Shields": 0,
          "Food": 0
        },
        "Row": 1,
        "Column": 3,
        "Type": "SelectBuilder",
        "AbilCmd": "SICommandCenterTrain,Train1",
        "id": "SelectBuilder",
        "Icon": "btn-upgrade-terran-weaponrefit",
        "Name": {
          "frFR": "Sélectionner constructeur ",
          "deDE": "Bauende Einheit auswählen ",
          "esES": "Seleccionar constructor ",
          "esMX": "Seleccionar constructor ",
          "ruRU": "Выбрать строителя ",
          "koKR": "건설 유닛 선택 ",
          "zhCN": "选择建造单位 ",
          "zhTW": "選取建造者 ",
          "plPL": "Wybierz budowniczego ",
          "itIT": "Seleziona costruttore",
          "ptBR": "Selecionar construtor "
        },
        "Tooltip": {
          "frFR": "Sélectionne l’unité qui construit ce bâtiment. ",
          "deDE": "Wählt die Einheit aus, die dieses Gebäude baut. ",
          "esES": "Selecciona a la unidad que está construyendo esta estructura. ",
          "esMX": "Selecciona a la unidad que está construyendo esta estructura. ",
          "ruRU": "Выбрать рабочего, который сооружает это строение. ",
          "koKR": "이 건물을 건설하고 있는 유닛을 선택합니다. ",
          "zhCN": "选中正在建造该建筑的单位。 ",
          "zhTW": "選取建造此建築的單位。 ",
          "plPL": "Wybierz jednostkę tworzącą tę budowlę. ",
          "itIT": "Seleziona l'unità che costruisce questa struttura.",
          "ptBR": "Seleciona a unidade que constrói esta estrutura. "
        }
      },
      {
        "Info": {
          "class": "CAbilBuildable",
          "Name": "Abil/Name/BuildInProgress",
          "TechPlayer": "Upkeep",
          "EditorCategories": "Race:Neutral,AbilityorEffectType:Units",
          "TargetMessage": "Abil/TargetMessage/DefaultTargetMessage",
          "OrderArray": [
            {
              "DisplayType": "Confirm",
              "Color": "255,0,255,0",
              "Model": "Assets\\UI\\Cursors\\WayPointConfirm_Void\\WayPointConfirm_Void.m3",
              "LineTexture": "Assets\\Textures\\WayPointLine.dds"
            }
          ],
          "SharedFlags": {
            "DisableWhileDead": 1
          },
          "DataCollection": "BuildInProgress",
          "Activity": "UI/Building",
          "VitalStartFactor": {
            "Life": 0.1,
            "Shields": 0.1,
            "Energy": 1
          },
          "CmdButtonArray": {
            "Cancel": {
              "DefaultButtonFace": "Cancel"
            },
            "Halt": {
              "DefaultButtonFace": "Cancel"
            }
          },
          "id": "BuildInProgress"
        },
        "Cost": {
          "Minerals": 0,
          "Vespene": 0,
          "Terazine": 0,
          "Custom": 0,
          "Energy": 0,
          "Life": 0,
          "Shields": 0,
          "Food": 0
        },
        "Row": 2,
        "Column": 3,
        "Type": "AbilCmd",
        "AbilCmd": "BuildInProgress,Halt",
        "id": "Halt",
        "Icon": "btn-command-stop",
        "Name": {
          "enUS": "Halt",
          "ruRU": "Приостановить ",
          "frFR": "Interrompre ",
          "deDE": "Anhalten ",
          "esES": "Parar ",
          "esMX": "Interrumpir ",
          "koKR": "중지 ",
          "zhCN": "暂停 ",
          "zhTW": "暫停 ",
          "plPL": "Wstrzymaj ",
          "itIT": "Interrompi",
          "ptBR": "Parar "
        },
        "Tooltip": {
          "frFR": "Interrompt la construction de ce bâtiment. La construction inachevée sera conservée. ",
          "deDE": "Hält den Bau dieses Gebäudes an. Das unfertige Gebäude bleibt bestehen. ",
          "esES": "Para la construcción de esta estructura. La construcción parcial se quedará donde está. ",
          "esMX": "Detiene la construcción de esta estructura. La construcción parcial seguirá existiendo. ",
          "ruRU": "Приостановить сооружение этого строения. Впоследствии его можно будет продолжить. ",
          "koKR": "건물 건설을 중지합니다. 건물은 건설 중인 상태로 유지됩니다. ",
          "zhCN": "暂停建造，保留尚未建造完成的建筑。 ",
          "zhTW": "暫停建造此建築。已建造的部分將保留。 ",
          "plPL": "Wstrzymuje wznoszenie budowli. Niedokończona budowla pozostanie na mapie. ",
          "itIT": "Interrompe la costruzione di questa struttura. La costruzione parziale resterà.",
          "ptBR": "Interrompe a construção dessa estrutura. A construção parcial permanecerá. "
        }
      },
      {
        "Info": {
          "class": "CAbilQueue",
          "Name": "Abil/Name/que5CancelToSelection",
          "TechPlayer": "Upkeep",
          "EditorCategories": "Race:Neutral,AbilityorEffectType:Structures",
          "TargetMessage": "Abil/TargetMessage/DefaultTargetMessage",
          "OrderArray": [
            {
              "DisplayType": "Confirm",
              "Color": "255,0,255,0",
              "Model": "Assets\\UI\\Cursors\\WayPointConfirm_Void\\WayPointConfirm_Void.m3",
              "LineTexture": "Assets\\Textures\\WayPointLine.dds"
            }
          ],
          "SharedFlags": {
            "DisableWhileDead": 1
          },
          "DataCollection": "que5CancelToSelection",
          "QueueCount": 1,
          "Flags": {
            "BestUnit": 1,
            "NotifyAddOn": 1
          },
          "CmdButtonArray": {
            "CancelLast": {
              "DefaultButtonFace": "Cancel",
              "Flags": {
                "ToSelection": 1
              }
            },
            "CancelSlot": {
              "DefaultButtonFace": "CancelSlot"
            }
          },
          "AbilSetId": "QueueCancelToSelection",
          "QueueSize": 5,
          "id": "que5CancelToSelection"
        },
        "Cost": {
          "Minerals": 0,
          "Vespene": 0,
          "Terazine": 0,
          "Custom": 0,
          "Energy": 0,
          "Life": 0,
          "Shields": 0,
          "Food": 0
        },
        "Row": 2,
        "Column": 4,
        "Type": "AbilCmd",
        "AbilCmd": "que5CancelToSelection,CancelLast",
        "id": "Cancel",
        "Icon": "btn-command-cancel",
        "Name": {
          "enUS": "Cancel",
          "ruRU": "Отменить ",
          "frFR": "Annuler ",
          "deDE": "Abbrechen ",
          "esES": "Cancelar ",
          "esMX": "Cancelar ",
          "koKR": "취소 ",
          "zhCN": "取消 ",
          "zhTW": "取消 ",
          "plPL": "Anuluj ",
          "itIT": "Annulla",
          "ptBR": "Cancelar "
        },
        "Tooltip": {
          "frFR": "Abandonne l’ordre en cours et vous permet d’en donner un nouveau. ",
          "deDE": "Bricht den aktuellen Befehl ab und ermöglicht das Erteilen neuer Befehle. ",
          "esES": "Abandona la orden actual sin llevarla a cabo y te permite seleccionar una orden diferente. ",
          "esMX": "Cancela la orden actual sin ejecutarla y te permite seleccionar otra orden. ",
          "ruRU": "Отменить текущий приказ и отдать следующий. ",
          "koKR": "유닛에게 내린 지시를 취소하여 다른 지시를 받을 수 있게 합니다. ",
          "zhCN": "直接取消当前命令，让您可以选择其它命令。 ",
          "zhTW": "直接取消目前的指令，這樣可讓你選擇不同的指令。 ",
          "plPL": "Porzuca aktualny rozkaz bez wykonywania go i pozwala wybrać inny. ",
          "itIT": "Annulla l'ordine attuale e consente di selezionarne un altro.",
          "ptBR": "Cancela a ordem atual sem executá-la e permite selecionar outra ordem. "
        }
      },
      {
        "Info": {
          "class": "CAbilBuildable",
          "Name": "Abil/Name/BuildInProgress",
          "TechPlayer": "Upkeep",
          "EditorCategories": "Race:Neutral,AbilityorEffectType:Units",
          "TargetMessage": "Abil/TargetMessage/DefaultTargetMessage",
          "OrderArray": [
            {
              "DisplayType": "Confirm",
              "Color": "255,0,255,0",
              "Model": "Assets\\UI\\Cursors\\WayPointConfirm_Void\\WayPointConfirm_Void.m3",
              "LineTexture": "Assets\\Textures\\WayPointLine.dds"
            }
          ],
          "SharedFlags": {
            "DisableWhileDead": 1
          },
          "DataCollection": "BuildInProgress",
          "Activity": "UI/Building",
          "VitalStartFactor": {
            "Life": 0.1,
            "Shields": 0.1,
            "Energy": 1
          },
          "CmdButtonArray": {
            "Cancel": {
              "DefaultButtonFace": "Cancel"
            },
            "Halt": {
              "DefaultButtonFace": "Cancel"
            }
          },
          "id": "BuildInProgress"
        },
        "Cost": {
          "Minerals": 0,
          "Vespene": 0,
          "Terazine": 0,
          "Custom": 0,
          "Energy": 0,
          "Life": 0,
          "Shields": 0,
          "Food": 0
        },
        "Row": 2,
        "Column": 4,
        "Type": "AbilCmd",
        "AbilCmd": "BuildInProgress,Cancel",
        "id": "CancelBuilding",
        "Icon": "btn-command-cancel",
        "Name": {
          "enUS": "Cancel Building",
          "ruRU": "Отменить ",
          "frFR": "Annuler ",
          "deDE": "Abbrechen ",
          "esES": "Cancelar ",
          "esMX": "Cancelar ",
          "koKR": "취소 ",
          "zhCN": "取消 ",
          "zhTW": "取消 ",
          "plPL": "Anuluj ",
          "itIT": "Annulla",
          "ptBR": "Cancelar "
        },
        "Tooltip": {
          "frFR": "Annule la construction de ce bâtiment. Il est détruit et une partie de son coût est remboursée. ",
          "deDE": "Bricht den Bau des Gebäudes ab, zerstört es und erstatt einen Teil der Ressourcen zurück. ",
          "esES": "Cancela la construcción de esta estructura, la destruye y devuelve parte de los recursos gastados. ",
          "esMX": "Cancela la construcción de esta estructura, destruyéndola y otorgando un reembolso parcial. ",
          "ruRU": "Отменить сооружение этого строения, уничтожив его и получив частичную компенсацию. ",
          "koKR": "건물의 건설을 취소합니다. 건설 중인 건물이 파괴되고 건설 비용의 일부를 돌려받습니다. ",
          "zhCN": "取消建造，摧毁尚未建造完成的建筑并返还部分资源。 ",
          "zhTW": "取消建造此建築，摧毀該建築並返還部分資源。 ",
          "plPL": "Anuluje wznoszenie budowli. Budowla zostaje zniszczona, a gracz otrzymuje częściowy zwrot kosztów budowy. ",
          "itIT": "Annulla la costruzione di questa struttura, distruggendola e ricavandone un parziale rimborso.",
          "ptBR": "Cancela a construção desta estrutura, destruindo a estrutura e executando uma devolução parcial. "
        }
      }
    ]
  },
  "Footprint": "Footprint3x3CreepStukov",
  "PlacementFootprint": "Footprint3x3CreepStukovPlacement",
  "SubgroupPriority": 62,
  "GlossaryCategory": "Unit/Category/InfestedTerranUnits",
  "HotkeyCategory": "Unit/Category/InfestedTerranUnits",
  "id": "SICivilianStructure",
  "Icon": "btn-building-stukov-infestedcolonisthut",
  "LifeArmorIcon": "btn-upgrade-terran-buildingarmor",
  "ShieldArmorIcon": "btn-upgrade-protoss-shieldslevel0",
  "Weapons": [],
  "Behaviors": [
    {
      "id": "SICivilianStructureSpawnCivilian",
      "Icon": "btn-missing-kaeo",
      "Name": "-",
      "Tooltip": "-"
    },
    {
      "id": "OnCreep",
      "Icon": "btn-missing-kaeo",
      "Name": "-",
      "Tooltip": "-"
    },
    {
      "id": "ZergBuildingNotOnCreep",
      "Icon": "btn-missing-kaeo",
      "Name": "-",
      "Tooltip": "-"
    },
    {
      "id": "ZergBuildingDies6",
      "Icon": "btn-missing-kaeo",
      "Name": "-",
      "Tooltip": "-"
    },
    {
      "id": "ChronoBoostTarget",
      "Icon": "btn-missing-kaeo",
      "Name": "-",
      "Tooltip": "-"
    }
  ],
  "Abilities": [
    {
      "id": "BuildInProgress",
      "Name": {
        "frFR": "Build in Progress",
        "deDE": "Build in Progress",
        "esES": "Build in Progress",
        "esMX": "Construcción en curso ",
        "ruRU": "Build in Progress",
        "koKR": "건설 중 ",
        "zhCN": "正在进行的建造 ",
        "zhTW": "正在建造中 ",
        "plPL": "Build in Progress",
        "itIT": "Build in Progress",
        "ptBR": "Construção em andamento "
      }
    },
    {
      "id": "que5",
      "Name": {
        "frFR": "Queue (5)",
        "deDE": "Queue (5)",
        "esES": "Queue (5)",
        "esMX": "Cola (5) ",
        "ruRU": "Queue (5)",
        "koKR": "대기열 (5) ",
        "zhCN": "队列(5) ",
        "zhTW": "佇列（5） ",
        "plPL": "Queue (5)",
        "itIT": "Queue (5)",
        "ptBR": "Fila (5) "
      }
    },
    {
      "id": "SIInfestedCivilianStructureResearch",
      "Name": {
        "frFR": "Infested Civilian Structure Research",
        "deDE": "Infested Civilian Structure Research",
        "esES": "Infested Civilian Structure Research",
        "esMX": "Estructura civil infestada - Investigación ",
        "ruRU": "Infested Civilian Structure Research",
        "koKR": "감염된 민간인 구조물 연구",
        "zhCN": "Infested Civilian Structure Research",
        "zhTW": "受感染的平民建築 - 研發",
        "plPL": "Infested Civilian Structure Research",
        "itIT": "Infested Civilian Structure Research",
        "ptBR": "Pesquisa de Estrutura de Civil Infestado "
      }
    },
    {
      "id": "SIStukovPlaceHordeRally",
      "Name": {
        "frFR": "SIStukovPlaceHordeRally",
        "deDE": "SIStukovPlaceHordeRally",
        "esES": "SIStukovPlaceHordeRally",
        "esMX": "SIStukovPlaceHordeRally ",
        "ruRU": "SIStukovPlaceHordeRally",
        "koKR": "SIStukovPlaceHordeRally",
        "zhCN": "SIStukovPlaceHordeRally",
        "zhTW": "SIStukovPlaceHordeRally",
        "plPL": "SIStukovPlaceHordeRally",
        "itIT": "SIStukovPlaceHordeRally",
        "ptBR": "SIStukovPlaceHordeRally "
      }
    },
    {
      "id": "SICivilianStructureLiftOff",
      "Name": "-"
    },
    {
      "id": "SICivilianStructureSpawnCivilian",
      "Name": "-"
    }
  ],
  "$Upgrades": [
    "SIBarracksTrainInfestedCivilianLevel2",
    "SICivilianStructure",
    "SIBarracksTrainInfestedCivilianLevel3",
    "SICivilianStructureFlying",
    "SICivilianStructureLand",
    "CountUnitSICivilianStructureCompleteOnlyAtUnit376386153",
    "SICivilianStructure",
    "SIBarracksTrainInfestedCivilianLevel4",
    "CountUnitSICivilianStructureInProgressOrBetter",
    "SIAdvancedBuild",
    "SICivilianStructure",
    "SIBuildingLand",
    "SICivilianStructureBurrowedSplat",
    "InfestedCivilianStructureSpawnCountLevel1",
    "InfestedCivilianStructureSpawnCountLevel2",
    "PlayerPrestige"
  ],
  "$Requirements": [],
  "$Production": [
    "Broodling"
  ],
  "$Research": [
    "SIBarracksTrainInfestedCivilianLevel2",
    "SIBarracksTrainInfestedCivilianLevel3",
    "SIBarracksTrainInfestedCivilianLevel4",
    "StukovInfestedInfestedCivilianLeapAttack",
    "StukovInfestedCivilianSpawnBroodlingOnDeath"
  ],
  "$Morph": [
    "SICivilianStructureFlying"
  ],
  "$Phase": [],
  "$Phased": "SICivilianStructureFlying",
  "$Producers": [
    "SISCV"
  ],
  "$Commands": [
    {
      "AbilCmd": "Rally,Rally1",
      "id": "Rally",
      "Icon": "btn-ability-terran-setrallypoint",
      "Name": {
        "frFR": "Définir le point de ralliement ",
        "deDE": "Sammelpunkt festlegen ",
        "esES": "Establecer punto de reunión ",
        "esMX": "Establecer punto de reunión ",
        "ruRU": "Задать точку сбора ",
        "koKR": "집결 지점 설정 ",
        "zhCN": "设定集结点 ",
        "zhTW": "設定集結點 ",
        "plPL": "Ustaw punkt zborny ",
        "itIT": "Imposta punto di raduno",
        "ptBR": "Definir ponto de concentração "
      },
      "Tooltip": {
        "frFR": "Envoie les unités construites au point désigné. Les ouvriers envoyés sur des ressources commenceront automatiquement la collecte. ",
        "deDE": "Schickt erstellte Einheiten zum festgelegten Punkt. Arbeiter, die zu Ressourcen geschickt werden, beginnen automatisch mit dem Abbau. ",
        "esES": "Envía a las unidades construidas al punto designado. Los obreros enviados a los recursos comenzarán a recolectar automáticamente. ",
        "esMX": "Envía las unidades construidas al punto designado. Los trabajadores reunidos en los recursos comenzarán automáticamente la recolección. ",
        "ruRU": "Отправляет созданные войска в указанную точку. Рабочие, отправленные на месторождение минералов или веспена, автоматически начнут добычу ресурсов.",
        "koKR": "생산된 유닛을 지정한 지점으로 보냅니다. 자원으로 보낸 일꾼은 자동으로 채취를 시작합니다. ",
        "zhCN": "将生成的单位派往指定地点。派往资源点的工作单位会自动开始采集。 ",
        "zhTW": "派遣所建造的單位前往指定的地點。被派往資源點的工作單位在抵達後將自動開始採集。 ",
        "plPL": "Wysyła nowowyszkolone jednostki we wskazane miejsce. Jednostki robotnicze wysłane do surowców automatycznie rozpoczną ich gromadzenie. ",
        "itIT": "Invia le unità prodotte verso il punto designato. I lavoratori radunati in prossimità di risorse inizieranno la raccolta automaticamente.",
        "ptBR": "Envia unidades construídas ao ponto designado. Os trabalhadores concentrados nos recursos começarão a extrair automaticamente. "
      }
    },
    {
      "AbilCmd": "SIStukovPlaceHordeRally,Execute",
      "id": "SIStukovPlaceHordeRally",
      "Icon": "btn-ability-zerg-stukov-summonpsiemitter",
      "Name": {
        "frFR": "Déploiement d’un émetteur psi",
        "deDE": "Psi-Emitter aktivieren",
        "esES": "Desplegar emisor psiónico",
        "esMX": "Desplegar Emisor psiónico ",
        "ruRU": "Установить пси-излучатель",
        "koKR": "사이오닉 방출기 배치 ",
        "zhCN": "部署灵能发射器 ",
        "zhTW": "設置幽能發射器 ",
        "plPL": "Emiter Psioniczny",
        "itIT": "Colloca Emettitore psionico",
        "ptBR": "Implantar Emissor Psi "
      },
      "Tooltip": {
        "frFR": "Envoie toutes les unités d’infanterie, existantes et formées récemment, à l’emplacement indiqué.",
        "deDE": "Schickt alle bestehenden und neu erschaffenen verseuchten Infanterieeinheiten zu einem bestimmten Punkt.",
        "esES": "Envía a todas las unidades de infantería infestadas existentes y recién construidas al punto seleccionado.",
        "esMX": "Envía a todas las unidades de Infantería infestadas, las que tenías y las que acabas de construir, al punto designado. ",
        "ruRU": "Отправляет всех существующих и порожденных в будущем зараженных пехотинцев в указанную точку.",
        "koKR": "현재 및 새롭게 생성되는 모든 감염된 보병 유닛을 목표 지점으로 보냅니다. ",
        "zhCN": "将当前已有和后续新造的被感染的步兵单位派往指定地点。 ",
        "zhTW": "將目前已有或是即將孵化的受感染的步兵單位集結到指定地點。 ",
        "plPL": "Wysyła wszystkie istniejące i nowo powstające jednostki zainfekowanej piechoty do wyznaczonego punktu.",
        "itIT": "Invia tutte le unità di fanteria infestate esistenti e appena generate al punto designato.",
        "ptBR": "Envia todas as unidades de infantaria Infestadas existentes e recém-construídas no momento para o ponto designado. "
      }
    },
    {
      "AbilCmd": "que5,CancelLast",
      "id": "Cancel",
      "Icon": "btn-command-cancel",
      "Name": {
        "enUS": "Cancel",
        "ruRU": "Отменить ",
        "frFR": "Annuler ",
        "deDE": "Abbrechen ",
        "esES": "Cancelar ",
        "esMX": "Cancelar ",
        "koKR": "취소 ",
        "zhCN": "取消 ",
        "zhTW": "取消 ",
        "plPL": "Anuluj ",
        "itIT": "Annulla",
        "ptBR": "Cancelar "
      },
      "Tooltip": {
        "frFR": "Abandonne l’ordre en cours et vous permet d’en donner un nouveau. ",
        "deDE": "Bricht den aktuellen Befehl ab und ermöglicht das Erteilen neuer Befehle. ",
        "esES": "Abandona la orden actual sin llevarla a cabo y te permite seleccionar una orden diferente. ",
        "esMX": "Cancela la orden actual sin ejecutarla y te permite seleccionar otra orden. ",
        "ruRU": "Отменить текущий приказ и отдать следующий. ",
        "koKR": "유닛에게 내린 지시를 취소하여 다른 지시를 받을 수 있게 합니다. ",
        "zhCN": "直接取消当前命令，让您可以选择其它命令。 ",
        "zhTW": "直接取消目前的指令，這樣可讓你選擇不同的指令。 ",
        "plPL": "Porzuca aktualny rozkaz bez wykonywania go i pozwala wybrać inny. ",
        "itIT": "Annulla l'ordine attuale e consente di selezionarne un altro.",
        "ptBR": "Cancela a ordem atual sem executá-la e permite selecionar outra ordem. "
      }
    },
    {
      "AbilCmd": "BuildInProgress,Cancel",
      "id": "Cancel",
      "Icon": "btn-command-cancel",
      "Name": {
        "enUS": "Cancel",
        "ruRU": "Отменить ",
        "frFR": "Annuler ",
        "deDE": "Abbrechen ",
        "esES": "Cancelar ",
        "esMX": "Cancelar ",
        "koKR": "취소 ",
        "zhCN": "取消 ",
        "zhTW": "取消 ",
        "plPL": "Anuluj ",
        "itIT": "Annulla",
        "ptBR": "Cancelar "
      },
      "Tooltip": {
        "frFR": "Abandonne l’ordre en cours et vous permet d’en donner un nouveau. ",
        "deDE": "Bricht den aktuellen Befehl ab und ermöglicht das Erteilen neuer Befehle. ",
        "esES": "Abandona la orden actual sin llevarla a cabo y te permite seleccionar una orden diferente. ",
        "esMX": "Cancela la orden actual sin ejecutarla y te permite seleccionar otra orden. ",
        "ruRU": "Отменить текущий приказ и отдать следующий. ",
        "koKR": "유닛에게 내린 지시를 취소하여 다른 지시를 받을 수 있게 합니다. ",
        "zhCN": "直接取消当前命令，让您可以选择其它命令。 ",
        "zhTW": "直接取消目前的指令，這樣可讓你選擇不同的指令。 ",
        "plPL": "Porzuca aktualny rozkaz bez wykonywania go i pozwala wybrać inny. ",
        "itIT": "Annulla l'ordine attuale e consente di selezionarne un altro.",
        "ptBR": "Cancela a ordem atual sem executá-la e permite selecionar outra ordem. "
      }
    },
    {
      "AbilCmd": "SICivilianStructureSpawnCivilian,Execute",
      "id": "SIInfestedCivilian",
      "Icon": "btn-unit-zerg-infestedcolonist",
      "Name": {
        "frFR": "Générer un civil contaminé",
        "deDE": "Verseuchten Zivilisten erschaffen",
        "esES": "Engendrar civil infestado",
        "esMX": "Engendrar Civil infestado ",
        "ruRU": "Породить зараженного мирного жителя",
        "koKR": "감염된 민간인 생성 ",
        "zhCN": "孵化被感染的平民 ",
        "zhTW": "孵化受感染的平民 ",
        "plPL": "Powij zainfekowanego cywila",
        "itIT": "Genera Civile infestato",
        "ptBR": "Gerar Civil Infestado "
      },
      "Tooltip": {
        "frFR": "Infanterie contaminée polyvalente. Dure <b>90</b> secondes.<br/><br/><span style=\"color: ##ffff8a\">Peut attaquer les unités terrestres.</span>",
        "deDE": "Verseuchte Allzweck-Infanterie. Bleibt <b>90</b> Sek. lang bestehen.<br/><br/><span style=\"color: ##ffff8a\">Kann Bodeneinheiten angreifen.</span>",
        "esES": "Infantería de cometido general infestada. Tiene una duración de <b>90</b> segundos.<br/><br/><span style=\"color: ##ffff8a\">Puede atacar a unidades terrestres.</span>",
        "esMX": "Infantería infestada de uso general. Dura <b>90</b> segundos.<br/><br/><span style=\"color: ##ffff8a\">Ataca a unidades terrestres.</span> ",
        "ruRU": "Зараженная пехота общего назначения. Продолжительность жизни – <b>90</b> сек.<br/><br/><span style=\"color: ##ffff8a\">Атакует только наземные цели.</span>",
        "koKR": "감염된 다목적 보병입니다. <b>90</b>초 동안 전장에 머뭅니다.<br/><br/><span style=\"color: ##ffff8a\">지상 유닛 공격 가능</span> ",
        "zhCN": "通用型被感染的步兵，持续存在<b>90</b>秒。<br/><br/><span style=\"color: ##ffff8a\">可以对地。</span> ",
        "zhTW": "泛用型受感染的步兵。可存活<b>90</b>秒。<br/><br/><span style=\"color: ##ffff8a\">可攻擊地面單位。</span> ",
        "plPL": "Zainfekowana piechota wielozadaniowa. Żyje <b>90</b> sek.<br/><br/><span style=\"color: ##ffff8a\">Może atakować jednostki naziemne.</span>",
        "itIT": "Fante generico infestato. Dura <b>90</b> secondi.<br/><br/><span style=\"color: ##ffff8a\">Può attaccare unità terrestri.</span>",
        "ptBR": "Infantaria infestada de uso geral. Tem uma duração de <b>90</b> segundos.<br/><br/><span style=\"color: ##ffff8a\">Ataca unidades terrestres.</span> "
      }
    },
    {
      "AbilCmd": "SIInfestedCivilianStructureResearch,Research1",
      "id": "ResearchSIBarracksTrainInfestedCivilianLevel2",
      "Icon": "btn-ability-stukov-infestedcivilianstructurelv1",
      "Name": {
        "frFR": "Évolution Contamination - Niv. 1",
        "deDE": "Verseuchung der Stufe 1 entwickeln",
        "esES": "Evolucionar nivel de infestación 1",
        "esMX": "Evolucionar Infestación nivel 1 ",
        "ruRU": "Развить заражение 1-го уровня",
        "koKR": "감염 진화 1단계 ",
        "zhCN": "进化1级感染 ",
        "zhTW": "進化感染等級1 ",
        "plPL": "Wyewoluuj infekcję poziomu 1",
        "itIT": "Evolvi Infestazione livello 1",
        "ptBR": "Evoluir Infestação Nível 1 "
      },
      "Tooltip": {
        "frFR": "Augmente de 500 les points de vie du <span style=\"color: #ffff8a\">baraquement contaminé</span> qui génère 8 <span style=\"color: #ffff8a\">civils contaminés</span> supplémentaires à la fois, pour un total de 16.",
        "deDE": "<span style=\"color: #ffff8a\">Verseuchte Koloniegebäude</span> erhalten zusätzlich +500 Trefferpunkte und erschaffen 8 weitere <span style=\"color: #ffff8a\">verseuchte Zivilisten</span> gleichzeitig, insgesamt 16.",
        "esES": "El <span style=\"color: #ffff8a\">complejo de colonos infestado</span> obtiene 500 de vida y engendra 8 <span style=\"color: #ffff8a\">civiles infestados</span> adicionales cada vez, hasta un total de 16.",
        "esMX": "El <span style=\"color: #ffff8a\">Complejo de colonos infestados</span> obtiene 500 de vida y engendra 8 <span style=\"color: #ffff8a\">Civiles infestados</span> más a la vez para alcanzar un total de 16. ",
        "ruRU": "Увеличивает запас прочности <span style=\"color: #ffff8a\">зараженного жилого модуля</span> на 500 ед., и позволяет ему каждый раз дополнительно порождать 8 <span style=\"color: #ffff8a\">зараженных мирных жителей</span> (всего 16).",
        "koKR": "<span style=\"color: #ffff8a\">감염된 거주민 수용소</span>의 체력이 500만큼 증가하고 추가로 한 번에 8기, 총 16기의 <span style=\"color: #ffff8a\">감염된 민간인</span>을 생성합니다. ",
        "zhCN": "<span style=\"color: #ffff8a\">被感染的移民营</span>获得500点生命值，并且同一时间可以孵化额外8名<span style=\"color: #ffff8a\">被感染的平民</span>，总共16名。 ",
        "zhTW": "<span style=\"color: #ffff8a\">受感染的殖民基地</span>生命值提高500點，一次可額外孵化8個<span style=\"color: #ffff8a\">受感染的平民</span>，共孵化16個。 ",
        "plPL": "<span style=\"color: #ffff8a\">Zainfekowana baza kolonistów</span> otrzymuje +500 pkt. życia i powija dodatkowych 8 <span style=\"color: #ffff8a\">zainfekowanych cywili</span> (łącznie 16).",
        "itIT": "Aumenta di 500 la vita del <span style=\"color: #ffff8a\">Complesso coloniale infestato</span> e genera 8 <span style=\"color: #ffff8a\">Civili infestati</span> aggiuntivi alla volta, per un totale di 16.",
        "ptBR": "O <span style=\"color: #ffff8a\">Complexo de Colonos Infestado</span> ganha 500 pontos de vida e gera 8 <span style=\"color: #ffff8a\">Civis Infestados</span> adicionais por vez, em um total de 16. "
      }
    },
    {
      "AbilCmd": "SIInfestedCivilianStructureResearch,Research2",
      "id": "ResearchSIBarracksTrainInfestedCivilianLevel3",
      "Icon": "btn-ability-stukov-infestedcivilianstructurelv2",
      "Name": {
        "frFR": "Évolution Contamination - Niv. 2",
        "deDE": "Verseuchung der Stufe 2 entwickeln",
        "esES": "Evolucionar nivel de infestación 2",
        "esMX": "Evolucionar Infestación nivel 2 ",
        "ruRU": "Развить заражение 2-го уровня",
        "koKR": "감염 진화 2단계 ",
        "zhCN": "进化2级感染 ",
        "zhTW": "進化感染等級2 ",
        "plPL": "Wyewoluuj infekcję poziomu 2",
        "itIT": "Evolvi Infestazione livello 2",
        "ptBR": "Evoluir Infestação Nível 2 "
      },
      "Tooltip": {
        "frFR": "Augmente de 500 les points de vie du <span style=\"color: #ffff8a\">baraquement contaminé</span> qui génère 16 <span style=\"color: #ffff8a\">civils contaminés</span> supplémentaires à la fois, pour un total de 32.",
        "deDE": "<span style=\"color: #ffff8a\">Verseuchte Koloniegebäude</span> erhalten zusätzlich +500 Trefferpunkte und erschaffen 16 weitere <span style=\"color: #ffff8a\">verseuchte Zivilisten</span> gleichzeitig, insgesamt 32.",
        "esES": "El <span style=\"color: #ffff8a\">complejo de colonos infestado</span> obtiene 500 de vida y engendra 16 <span style=\"color: #ffff8a\">civiles infestados</span> adicionales cada vez, hasta un total de 32.",
        "esMX": "El <span style=\"color: #ffff8a\">Complejo de colonos infestados</span> obtiene 500 de vida y engendra 16 <span style=\"color: #ffff8a\">Civiles infestados</span> más de una vez para alcanzar un total de 32. ",
        "ruRU": "Увеличивает запас прочности <span style=\"color: #ffff8a\">зараженного жилого модуля</span> на 500 ед., и позволяет ему каждый раз дополнительно порождать 16 <span style=\"color: #ffff8a\">зараженных мирных жителей</span> (всего 32).",
        "koKR": "<span style=\"color: #ffff8a\">감염된 거주민 수용소</span>의 체력이 500만큼 증가하고 추가로 한 번에 16기, 총 32기의 <span style=\"color: #ffff8a\">감염된 민간인</span>을 생성합니다. ",
        "zhCN": "<span style=\"color: #ffff8a\">被感染的移民营</span>额外获得500点生命值，并且同一时间可以孵化额外16名<span style=\"color: #ffff8a\">被感染的平民</span>，总共32名。 ",
        "zhTW": "<span style=\"color: #ffff8a\">受感染的殖民基地</span>生命值再提高500點，一次可額外孵化16個<span style=\"color: #ffff8a\">受感染的平民</span>，共孵化32個。 ",
        "plPL": "<span style=\"color: #ffff8a\">Zainfekowana baza kolonistów</span> otrzymuje +500 pkt. życia i powija dodatkowych 16 <span style=\"color: #ffff8a\">zainfekowanych cywili</span> (łącznie 32).",
        "itIT": "Aumenta ulteriormente di 500 la vita del <span style=\"color: #ffff8a\">Complesso coloniale infestato</span> e genera 16 <span style=\"color: #ffff8a\">Civili infestati</span> aggiuntivi alla volta, per un totale di 32.",
        "ptBR": "O <span style=\"color: #ffff8a\">Complexo de Colonos Infestado</span> ganha 500 pontos de vida adicionais e gera 16 <span style=\"color: #ffff8a\">Civis Infestados</span> adicionais por vez, em um total de 32. "
      }
    },
    {
      "AbilCmd": "SIInfestedCivilianStructureResearch,Research3",
      "id": "ResearchSIBarracksTrainInfestedCivilianLevel4",
      "Icon": "btn-ability-stukov-infestedcivilianstructure_lv3",
      "Name": {
        "frFR": "Évolution Contamination - Niv. 3",
        "deDE": "Verseuchung der Stufe 3 entwickeln",
        "esES": "Evolucionar nivel de infestación 3",
        "esMX": "Evolucionar Infestación nivel 3 ",
        "ruRU": "Развить заражение 3-го уровня",
        "koKR": "감염 진화 3단계 ",
        "zhCN": "进化3级感染 ",
        "zhTW": "進化感染等級3 ",
        "plPL": "Wyewoluuj infekcję poziomu 3",
        "itIT": "Evolvi Infestazione livello 3",
        "ptBR": "Evoluir Infestação Nível 3 "
      },
      "Tooltip": {
        "frFR": "Augmente de 500 les points de vie du <span style=\"color: #ffff8a\">baraquement contaminé</span> qui génère 32 <span style=\"color: #ffff8a\">civils contaminés</span> supplémentaires à la fois, pour un total de 64.",
        "deDE": "<span style=\"color: #ffff8a\">Verseuchte Koloniegebäude</span> erhalten zusätzlich +500 Trefferpunkte und erschaffen 32 weitere <span style=\"color: #ffff8a\">verseuchte Zivilisten</span> gleichzeitig, insgesamt 64.",
        "esES": "El <span style=\"color: #ffff8a\">complejo de colonos infestado</span> obtiene 500 de vida y engendra 32 <span style=\"color: #ffff8a\">civiles infestados</span> adicionales cada vez, hasta un total de 64.",
        "esMX": "El <span style=\"color: #ffff8a\">Complejo de colonos infestados</span> obtiene 500 de vida y engendra 32 <span style=\"color: #ffff8a\">Civiles infestados</span> más de una vez para alcanzar un total de 64. ",
        "ruRU": "Увеличивает запас прочности <span style=\"color: #ffff8a\">зараженного жилого модуля</span> на 500 ед., и позволяет ему каждый раз дополнительно порождать 32 <span style=\"color: #ffff8a\">зараженных мирных жителя</span> (всего 64).",
        "koKR": "<span style=\"color: #ffff8a\">감염된 거주민 수용소</span>의 체력이 500만큼 증가하고 추가로 한 번에 32기, 총 64기의 <span style=\"color: #ffff8a\">감염된 민간인</span>을 생성합니다. ",
        "zhCN": "<span style=\"color: #ffff8a\">被感染的移民营</span>额外获得500点生命值，并且同一时间可以孵化额外32名<span style=\"color: #ffff8a\">被感染的平民</span>，总共64名。 ",
        "zhTW": "<span style=\"color: #ffff8a\">受感染的殖民基地</span>生命值再提高500點，一次可額外孵化32個<span style=\"color: #ffff8a\">受感染的平民</span>，共孵化64個。 ",
        "plPL": "<span style=\"color: #ffff8a\">Zainfekowana baza kolonistów</span> otrzymuje +500 pkt. życia i powija dodatkowych 32 <span style=\"color: #ffff8a\">zainfekowanych cywili</span> (łącznie 64).",
        "itIT": "Aumenta ulteriormente di 500 la vita del <span style=\"color: #ffff8a\">Complesso coloniale infestato</span> e genera 32 <span style=\"color: #ffff8a\">Civili infestati</span> aggiuntivi alla volta, per un totale di 64.",
        "ptBR": "O <span style=\"color: #ffff8a\">Complexo de Colonos Infestado</span> ganha 500 pontos de vida adicionais e gera 32 <span style=\"color: #ffff8a\">Civis Infestados</span> adicionais por vez, em um total de 64. "
      }
    },
    {
      "AbilCmd": "SICivilianStructureLiftOff,Execute",
      "id": "SIUproot",
      "Icon": "btn-ability-zerg-uproot-color",
      "Name": {
        "frFR": "Déraciner",
        "deDE": "Entwurzeln",
        "esES": "Desarraigar",
        "esMX": "Desarraigar ",
        "ruRU": "Выкопаться",
        "koKR": "뿌리 들기 ",
        "zhCN": "站起 ",
        "zhTW": "拔根 ",
        "plPL": "Wykorzeń",
        "itIT": "Sradica",
        "ptBR": "Desenraizar "
      },
      "Tooltip": {
        "frFR": "Déracine le bâtiment, lui permettant de se déplacer librement. Il sera impossible de produire des unités, rechercher des améliorations ou utiliser des capacités spéciales avant l’enracinement.",
        "deDE": "Entwurzelt das Gebäude, sodass es sich frei bewegen kann. Es können keine Einheiten erschaffen, Upgrades erforscht oder Fähigkeiten eingesetzt werden, bis das Gebäude wieder verwurzelt ist.",
        "esES": "Desarraiga la estructura, lo que le permite moverse con libertad. No puede producir unidades, investigar mejoras ni usar habilidades hasta que se arraigue.",
        "esMX": "Desarraiga la estructura y le permite moverse con libertad. Hasta que se arraigue otra vez, no podrá producir unidades, investigar mejoras ni usar habilidades. ",
        "ruRU": "Выкопать строение, дав ему возможность свободно передвигаться. Строение не сможет производить войска, проводить исследования, а также использовать специальные возможности, пока не окопается.",
        "koKR": "구조물의 뿌리를 들어 자유롭게 이동할 수 있게 만듭니다. 다시 뿌리를 박을 때까지 유닛 생산, 업그레이드 연구, 능력 사용이 불가능합니다. ",
        "zhCN": "使建筑站起，允许其可以自由移动。在扎根之前无法生产单位、研究升级、或者使用技能。 ",
        "zhTW": "命令建築拔根，使它能自由移動。直到再度扎根前，無法生產單位、研發升級或使用技能。 ",
        "plPL": "Wykorzenia budowlę i pozwala jej się swobodnie przemieszczać. Nie pozwala produkować jednostek, opracowywać ulepszeń ani korzystać ze zdolności, dopóki budowla nie zostanie znowu zakorzeniona.",
        "itIT": "Sradica la struttura, consentendole di spostarsi liberamente. Finché non si radica, non è in grado di produrre unità, ricercare potenziamenti o usare abilità.",
        "ptBR": "Desenraiza a estrutura, permitindo que se mova livremente. Ela não pode produzir unidades, pesquisar aprimoramentos ou usar habilidades até ser enraizada. "
      }
    },
    {
      "AbilCmd": "SIInfestedCivilianStructureResearch,Research11",
      "id": "EvolveStukovInfestedInfestedCivilianLeap",
      "Icon": "btn-upgrade-zerg-stukov-infestedciviliansleap",
      "Name": {
        "frFR": "Rechercher Métabolisme anaérobie",
        "deDE": "Erhöhte Sprungkraft erforschen",
        "esES": "Investigar mejora anaeróbica",
        "esMX": "Investigar Mejora anaeróbica ",
        "ruRU": "Разработать анаэробное усиление",
        "koKR": "혐기성 도약 연구 ",
        "zhCN": "研究厌氧强化 ",
        "zhTW": "研發瞬間體能強化 ",
        "plPL": "Opracuj wzmocnienie anaerobowe",
        "itIT": "Ricerca Incremento anaerobico",
        "ptBR": "Pesquisar Aprimoramento Anaeróbico "
      },
      "Tooltip": {
        "frFR": "Permet aux <span style=\"color: #ffff8a\">civils contaminés</span> de bondir rapidement en direction des unités terrestres ennemies proches.",
        "deDE": "Ermöglicht es <span style=\"color: #ffff8a\">verseuchten Zivilisten</span>, schnell zu einer feindlichen Bodeneinheit in der Nähe zu springen.",
        "esES": "Permite a los <span style=\"color: #ffff8a\">civiles infestados</span> saltar rápidamente hacia unidades terrestres enemigas cercanas.",
        "esMX": "Permite que los <span style=\"color: #ffff8a\">Civiles infestados</span> salten rápidamente hacia las unidades terrestres enemigas cercanas. ",
        "ruRU": "Позволяет <span style=\"color: #ffff8a\">зараженным мирным жителям</span> быстро прыгать к находящимся поблизости наземным боевым единицам противника.",
        "koKR": "<span style=\"color: #ffff8a\">감염된 민간인</span>이 주위의 적 지상 유닛에게 빠르게 도약할 수 있게 합니다. ",
        "zhCN": "允许<span style=\"color: #ffff8a\">被感染的平民</span>快速扑向附近的敌方地面单位。 ",
        "zhTW": "讓<span style=\"color: #ffff8a\">受感染的平民</span>可快速躍向附近的敵方地面單位。 ",
        "plPL": "Pozwala <span style=\"color: #ffff8a\">zainfekowanym cywilom</span> szybko doskakiwać do pobliskich jednostek naziemnych wroga.",
        "itIT": "Consente ai <span style=\"color: #ffff8a\">Civili infestati</span> di saltare rapidamente verso le unità terrestri nemiche.",
        "ptBR": "Permite que <span style=\"color: #ffff8a\">Civis Infestados</span> saltem rapidamente na direção de unidades terrestres inimigas próximas. "
      }
    },
    {
      "AbilCmd": "SIInfestedCivilianStructureResearch,Research10",
      "id": "EvolveStukovInfestedCivilianSpawnBroodlingsOnDeath",
      "Icon": "btn-upgrade-zerg-stukov-infestedspawnbroodling",
      "Name": {
        "frFR": "Évolution Incubation de vermine",
        "deDE": "Parasitenbefall entwickeln",
        "esES": "Evolucionar gestación de crías",
        "esMX": "Evolucionar Gestación de Ácaros ",
        "ruRU": "Развить созревание симбионта",
        "koKR": "공생충 잉태 진화 ",
        "zhCN": "进化巢虫育生 ",
        "zhTW": "進化寄生蟲宿主 ",
        "plPL": "Wyewoluuj rozwój pomiotów",
        "itIT": "Evolvi Gestazione Progenidi",
        "ptBR": "Evoluir Gestação de Parasitoides "
      },
      "Tooltip": {
        "frFR": "Les <span style=\"color: #ffff8a\">civils contaminés</span> génèrent une vermine quand ils meurent.",
        "deDE": "Aus <span style=\"color: #ffff8a\">verseuchten Zivilisten</span> schlüpft nach ihrem Tod ein Brütling.",
        "esES": "Los <span style=\"color: #ffff8a\">civiles infestados</span> engendran una cría al morir.",
        "esMX": "Los <span style=\"color: #ffff8a\">Civiles infestados</span> engendran un Ácaro cuando mueren. ",
        "ruRU": "<span style=\"color: #ffff8a\">Зараженные мирные жители</span> порождают симбионтов в момент гибели.",
        "koKR": "<span style=\"color: #ffff8a\">감염된 민간인</span>이 죽으면 공생충 한 마리를 생성합니다. ",
        "zhCN": "<span style=\"color: #ffff8a\">被感染的平民</span>死后会孵化一只巢虫。 ",
        "zhTW": "<span style=\"color: #ffff8a\">受感染的平民</span>死亡時會孵化寄生蟲。 ",
        "plPL": "<span style=\"color: #ffff8a\">Zainfekowani cywile</span> powijają w chwili śmierci pomioty.",
        "itIT": "I <span style=\"color: #ffff8a\">Civili infestati</span> generano un Progenide alla morte.",
        "ptBR": "<span style=\"color: #ffff8a\">Civis Infestados</span> geram um Parasitoide ao morrer. "
      }
    },
    {
      "AbilCmd": "SICommandCenterTrain,Train1",
      "id": "SelectBuilder",
      "Icon": "btn-upgrade-terran-weaponrefit",
      "Name": {
        "frFR": "Sélectionner constructeur ",
        "deDE": "Bauende Einheit auswählen ",
        "esES": "Seleccionar constructor ",
        "esMX": "Seleccionar constructor ",
        "ruRU": "Выбрать строителя ",
        "koKR": "건설 유닛 선택 ",
        "zhCN": "选择建造单位 ",
        "zhTW": "選取建造者 ",
        "plPL": "Wybierz budowniczego ",
        "itIT": "Seleziona costruttore",
        "ptBR": "Selecionar construtor "
      },
      "Tooltip": {
        "frFR": "Sélectionne l’unité qui construit ce bâtiment. ",
        "deDE": "Wählt die Einheit aus, die dieses Gebäude baut. ",
        "esES": "Selecciona a la unidad que está construyendo esta estructura. ",
        "esMX": "Selecciona a la unidad que está construyendo esta estructura. ",
        "ruRU": "Выбрать рабочего, который сооружает это строение. ",
        "koKR": "이 건물을 건설하고 있는 유닛을 선택합니다. ",
        "zhCN": "选中正在建造该建筑的单位。 ",
        "zhTW": "選取建造此建築的單位。 ",
        "plPL": "Wybierz jednostkę tworzącą tę budowlę. ",
        "itIT": "Seleziona l'unità che costruisce questa struttura.",
        "ptBR": "Seleciona a unidade que constrói esta estrutura. "
      }
    },
    {
      "AbilCmd": "BuildInProgress,Halt",
      "id": "Halt",
      "Icon": "btn-command-stop",
      "Name": {
        "enUS": "Halt",
        "ruRU": "Приостановить ",
        "frFR": "Interrompre ",
        "deDE": "Anhalten ",
        "esES": "Parar ",
        "esMX": "Interrumpir ",
        "koKR": "중지 ",
        "zhCN": "暂停 ",
        "zhTW": "暫停 ",
        "plPL": "Wstrzymaj ",
        "itIT": "Interrompi",
        "ptBR": "Parar "
      },
      "Tooltip": {
        "frFR": "Interrompt la construction de ce bâtiment. La construction inachevée sera conservée. ",
        "deDE": "Hält den Bau dieses Gebäudes an. Das unfertige Gebäude bleibt bestehen. ",
        "esES": "Para la construcción de esta estructura. La construcción parcial se quedará donde está. ",
        "esMX": "Detiene la construcción de esta estructura. La construcción parcial seguirá existiendo. ",
        "ruRU": "Приостановить сооружение этого строения. Впоследствии его можно будет продолжить. ",
        "koKR": "건물 건설을 중지합니다. 건물은 건설 중인 상태로 유지됩니다. ",
        "zhCN": "暂停建造，保留尚未建造完成的建筑。 ",
        "zhTW": "暫停建造此建築。已建造的部分將保留。 ",
        "plPL": "Wstrzymuje wznoszenie budowli. Niedokończona budowla pozostanie na mapie. ",
        "itIT": "Interrompe la costruzione di questa struttura. La costruzione parziale resterà.",
        "ptBR": "Interrompe a construção dessa estrutura. A construção parcial permanecerá. "
      }
    },
    {
      "AbilCmd": "que5CancelToSelection,CancelLast",
      "id": "Cancel",
      "Icon": "btn-command-cancel",
      "Name": {
        "enUS": "Cancel",
        "ruRU": "Отменить ",
        "frFR": "Annuler ",
        "deDE": "Abbrechen ",
        "esES": "Cancelar ",
        "esMX": "Cancelar ",
        "koKR": "취소 ",
        "zhCN": "取消 ",
        "zhTW": "取消 ",
        "plPL": "Anuluj ",
        "itIT": "Annulla",
        "ptBR": "Cancelar "
      },
      "Tooltip": {
        "frFR": "Abandonne l’ordre en cours et vous permet d’en donner un nouveau. ",
        "deDE": "Bricht den aktuellen Befehl ab und ermöglicht das Erteilen neuer Befehle. ",
        "esES": "Abandona la orden actual sin llevarla a cabo y te permite seleccionar una orden diferente. ",
        "esMX": "Cancela la orden actual sin ejecutarla y te permite seleccionar otra orden. ",
        "ruRU": "Отменить текущий приказ и отдать следующий. ",
        "koKR": "유닛에게 내린 지시를 취소하여 다른 지시를 받을 수 있게 합니다. ",
        "zhCN": "直接取消当前命令，让您可以选择其它命令。 ",
        "zhTW": "直接取消目前的指令，這樣可讓你選擇不同的指令。 ",
        "plPL": "Porzuca aktualny rozkaz bez wykonywania go i pozwala wybrać inny. ",
        "itIT": "Annulla l'ordine attuale e consente di selezionarne un altro.",
        "ptBR": "Cancela a ordem atual sem executá-la e permite selecionar outra ordem. "
      }
    },
    {
      "AbilCmd": "BuildInProgress,Cancel",
      "id": "CancelBuilding",
      "Icon": "btn-command-cancel",
      "Name": {
        "enUS": "Cancel Building",
        "ruRU": "Отменить ",
        "frFR": "Annuler ",
        "deDE": "Abbrechen ",
        "esES": "Cancelar ",
        "esMX": "Cancelar ",
        "koKR": "취소 ",
        "zhCN": "取消 ",
        "zhTW": "取消 ",
        "plPL": "Anuluj ",
        "itIT": "Annulla",
        "ptBR": "Cancelar "
      },
      "Tooltip": {
        "frFR": "Annule la construction de ce bâtiment. Il est détruit et une partie de son coût est remboursée. ",
        "deDE": "Bricht den Bau des Gebäudes ab, zerstört es und erstatt einen Teil der Ressourcen zurück. ",
        "esES": "Cancela la construcción de esta estructura, la destruye y devuelve parte de los recursos gastados. ",
        "esMX": "Cancela la construcción de esta estructura, destruyéndola y otorgando un reembolso parcial. ",
        "ruRU": "Отменить сооружение этого строения, уничтожив его и получив частичную компенсацию. ",
        "koKR": "건물의 건설을 취소합니다. 건설 중인 건물이 파괴되고 건설 비용의 일부를 돌려받습니다. ",
        "zhCN": "取消建造，摧毁尚未建造完成的建筑并返还部分资源。 ",
        "zhTW": "取消建造此建築，摧毀該建築並返還部分資源。 ",
        "plPL": "Anuluje wznoszenie budowli. Budowla zostaje zniszczona, a gracz otrzymuje częściowy zwrot kosztów budowy. ",
        "itIT": "Annulla la costruzione di questa struttura, distruggendola e ricavandone un parziale rimborso.",
        "ptBR": "Cancela a construção desta estrutura, destruindo a estrutura e executando uma devolução parcial. "
      }
    }
  ]
}