{
  "DeathRevealFilters": "Visible;Player,Ally,Neutral,Missile,Dead,Hidden",
  "DeathRevealRadius": 2,
  "DeathRevealDuration": 4,
  "DeathRevealType": "Snapshot",
  "Race": "Prot",
  "DefaultAcquireLevel": "Offensive",
  "Response": "Acquire",
  "ResourceState": "Unknown",
  "ResourceType": "Unknown",
  "LifeStart": 10000,
  "LifeMax": 10000,
  "LifeArmorName": "None",
  "Mover": "Ground",
  "StationaryTurningRate": 720,
  "TurningRate": 720,
  "Radius": 0.5,
  "SeparationRadius": 0.5,
  "MinimapRadius": 0,
  "EditorCategories": "ObjectType:Unit,ObjectFamily:Campaign",
  "TacticalAIFilters": "-;Player,Ally,Neutral",
  "AIEvalFactor": 1,
  "Mass": 0.4,
  "FlagArray": [
    "Movable",
    "Unclickable",
    "Unhighlightable",
    "Untooltipable",
    "KillCredit",
    "ShowResources",
    "ClearRallyOnTargetLost",
    "PlayerRevivable",
    "CameraFollow",
    "Untargetable",
    "Invulnerable",
    "NoPortraitTalk",
    "Unstoppable"
  ],
  "EditorFlags": [
    "BlockStructures"
  ],
  "PushPriority": 10,
  "LeaderAlias": "AncientXelNagaArtifact",
  "HotkeyAlias": "AncientXelNagaArtifact",
  "SelectAlias": "AncientXelNagaArtifact",
  "SubgroupAlias": "AncientXelNagaArtifact",
  "OccludeHeight": 0.75,
  "TacticalAI": "AncientXelNagaArtifact",
  "AIEvaluateAlias": "AncientXelNagaArtifact",
  "ReviveType": "AncientXelNagaArtifact",
  "PawnItemReduction": 1,
  "Fidget": {
    "DelayMax": 30,
    "DelayMin": 10,
    "DistanceMax": 4,
    "DistanceMin": 1,
    "TurnAngle": 90,
    "TurningRate": 90,
    "ChanceArray": {
      "Idle": 100
    }
  },
  "ReviveInfoBase": {
    "Charge": {
      "Link": "AncientXelNagaArtifact/Revive",
      "Location": "Unit"
    },
    "Cooldown": {
      "Link": "AncientXelNagaArtifact/Revive",
      "Location": "Unit"
    }
  },
  "InnerRadiusSafetyMultiplier": 1,
  "ArmorType": "Unknown",
  "$tokens": {
    "ID": {
      "type": "string",
      "value": ""
    }
  },
  "Mob": "Campaign",
  "Height": 0.1,
  "CardLayouts": {
    "Root": []
  },
  "Footprint": "Footprint4x4Contour",
  "PlacementFootprint": "Footprint4x4Contour",
  "id": "AncientXelNagaArtifact",
  "Weapons": [],
  "Behaviors": [],
  "Abilities": [],
  "$Upgrades": [
    "AncientXelNagaArtifact"
  ],
  "$Requirements": [],
  "$Production": [],
  "$Research": [],
  "$Morph": [],
  "$Phase": [],
  "$Producers": [],
  "$Commands": []
}